{
  "updated_at": "2026-01-04T01:11:10.909289Z",
  "solar": {
    "sunspots": "136",
    "solarflux": "165",
    "aindex": " 12",
    "kindex": " 1",
    "solarwind": "444.7",
    "signalnoise": "S0-S1",
    "xray": "C1.2",
    "geomagfield": "VR QUIET",
    "electonflux": "3390",
    "protonflux": "137"
  },
  "hf_bands": {
    "80m_40m": {
      "day": "Poor",
      "night": "Good"
    },
    "30m_20m": {
      "day": "Good",
      "night": "Good"
    },
    "17m_15m": {
      "day": "Good",
      "night": "Good"
    },
    "12m_10m": {
      "day": "Good",
      "night": "Poor"
    }
  }
}