{
  "updated_at": "2026-01-21T12:30:58.799042Z",
  "solar": {
    "sunspots": "181",
    "solarflux": "178",
    "aindex": " 143",
    "kindex": " 6",
    "solarwind": "642.6",
    "signalnoise": "S6-S9",
    "xray": "C2.2",
    "geomagfield": "MAJ STRM",
    "electonflux": "75100",
    "protonflux": "1090"
  },
  "hf_bands": {
    "80m_40m": {
      "day": "Poor",
      "night": "Poor"
    },
    "30m_20m": {
      "day": "Poor",
      "night": "Poor"
    },
    "17m_15m": {
      "day": "Poor",
      "night": "Poor"
    },
    "12m_10m": {
      "day": "Poor",
      "night": "Poor"
    }
  }
}