{
  "updated_at": "2026-07-08T21:58:37.009108Z",
  "solar": {
    "sunspots": "81",
    "solarflux": "116",
    "aindex": " 12",
    "kindex": " 2",
    "solarwind": "399.0",
    "signalnoise": "S1-S2",
    "xray": "B7.2",
    "geomagfield": "QUIET",
    "electonflux": "1820",
    "protonflux": "47"
  },
  "hf_bands": {
    "80m_40m": {
      "day": "Fair",
      "night": "Good"
    },
    "30m_20m": {
      "day": "Good",
      "night": "Good"
    },
    "17m_15m": {
      "day": "Fair",
      "night": "Fair"
    },
    "12m_10m": {
      "day": "Poor",
      "night": "Poor"
    }
  }
}