[
  {
    "fullCallsign": "N1RWJ",
    "callsign": "N1RWJ",
    "frequency": "10.118",
    "band": "30m",
    "mode": "cw",
    "modeDetail": "cw",
    "time": "22:09",
    "spotter": "WE9V",
    "snr": 14,
    "speed": 20,
    "rawText": "DX de WE9V-#:   10118.00  N1RWJ          CW    14 dB  20 WPM  CQ      2209Z",
    "title": "RBN spot N1RWJ (10.118 CW)",
    "source": "rbn",
    "state": "US_RI",
    "spotterState": "US_WI",
    "qsl": "eqsl,lotw",
    "dxcc": 291,
    "entity": "United States of America",
    "cq": "5",
    "continent": "NA",
    "homeDxcc": 291,
    "homeEntity": "United States of America",
    "spotterDxcc": 291,
    "spotterEntity": "United States of America",
    "spotterCq": "4",
    "spotterContinent": "NA",
    "triggerComment": "EDH Discord",
    "received_at": "2026-06-20T22:09:22.747344Z"
  },
  {
    "fullCallsign": "N1RWJ",
    "callsign": "N1RWJ",
    "frequency": "10.118",
    "band": "30m",
    "mode": "cw",
    "modeDetail": "cw",
    "time": "21:57",
    "spotter": "W4VE",
    "rawText": "21:57 N1RWJ in US-1738 (Fox Point State Park) 10.1180 CW: 73 from Florida \ud83d\ude4b\u200d\u2642\ufe0f",
    "title": "POTA N1RWJ in US-1738 (10.1180 CW)",
    "comment": "73 from Florida \ud83d\ude4b\u200d\u2642\ufe0f",
    "source": "pota",
    "state": [
      "US_DE"
    ],
    "spotterState": "US_FL",
    "wwffRef": "US-1738",
    "wwffDivision": "US",
    "wwffName": "Fox Point State Park",
    "qsl": "eqsl,lotw",
    "dxcc": 291,
    "entity": "United States of America",
    "cq": "5",
    "continent": "NA",
    "homeDxcc": 291,
    "homeEntity": "United States of America",
    "spotterDxcc": 291,
    "spotterEntity": "United States of America",
    "spotterCq": "5",
    "spotterContinent": "NA",
    "triggerComment": "EDH Discord",
    "received_at": "2026-06-20T21:58:41.544309Z"
  },
  {
    "fullCallsign": "N1RWJ",
    "callsign": "N1RWJ",
    "frequency": "10.118",
    "band": "30m",
    "mode": "cw",
    "modeDetail": "cw",
    "time": "21:48",
    "spotter": "WE9V",
    "snr": 12,
    "speed": 20,
    "rawText": "DX de WE9V-#:   10118.00  N1RWJ          CW    12 dB  20 WPM  CQ      2148Z",
    "title": "RBN spot N1RWJ (10.118 CW)",
    "source": "rbn",
    "state": "US_RI",
    "spotterState": "US_WI",
    "qsl": "eqsl,lotw",
    "dxcc": 291,
    "entity": "United States of America",
    "cq": "5",
    "continent": "NA",
    "homeDxcc": 291,
    "homeEntity": "United States of America",
    "spotterDxcc": 291,
    "spotterEntity": "United States of America",
    "spotterCq": "4",
    "spotterContinent": "NA",
    "triggerComment": "EDH Discord",
    "received_at": "2026-06-20T21:48:39.096921Z"
  },
  {
    "fullCallsign": "N1RWJ",
    "callsign": "N1RWJ",
    "frequency": "10.118",
    "band": "30m",
    "mode": "cw",
    "modeDetail": "cw",
    "time": "21:38",
    "spotter": "WE9V",
    "snr": 15,
    "speed": 20,
    "rawText": "DX de WE9V-#:   10118.00  N1RWJ          CW    15 dB  20 WPM  CQ      2138Z",
    "title": "RBN spot N1RWJ (10.118 CW)",
    "source": "rbn",
    "state": "US_RI",
    "spotterState": "US_WI",
    "qsl": "eqsl,lotw",
    "dxcc": 291,
    "entity": "United States of America",
    "cq": "5",
    "continent": "NA",
    "homeDxcc": 291,
    "homeEntity": "United States of America",
    "spotterDxcc": 291,
    "spotterEntity": "United States of America",
    "spotterCq": "4",
    "spotterContinent": "NA",
    "triggerComment": "EDH Discord",
    "received_at": "2026-06-20T21:38:27.647623Z"
  },
  {
    "fullCallsign": "N1RWJ",
    "callsign": "N1RWJ",
    "frequency": "10.118",
    "band": "30m",
    "mode": "cw",
    "modeDetail": "cw",
    "time": "21:28",
    "spotter": "VE3EID",
    "snr": 21,
    "speed": 19,
    "rawText": "DX de VE3EID-#: 10118.00  N1RWJ          CW    21 dB  19 WPM  CQ      2128Z",
    "title": "RBN spot N1RWJ (10.118 CW)",
    "source": "rbn",
    "state": "US_RI",
    "spotterState": "CA_ON",
    "qsl": "eqsl,lotw",
    "dxcc": 291,
    "entity": "United States of America",
    "cq": "5",
    "continent": "NA",
    "homeDxcc": 291,
    "homeEntity": "United States of America",
    "spotterDxcc": 1,
    "spotterEntity": "Canada",
    "spotterCq": "4",
    "spotterContinent": "NA",
    "triggerComment": "EDH Discord",
    "received_at": "2026-06-20T21:28:23.680367Z"
  },
  {
    "fullCallsign": "N1RWJ",
    "callsign": "N1RWJ",
    "frequency": "7.039",
    "band": "40m",
    "mode": "cw",
    "modeDetail": "cw",
    "time": "20:07",
    "spotter": "KM3T-3",
    "snr": 17,
    "speed": 20,
    "rawText": "DX de KM3T-3-#:  7039.00  N1RWJ          CW    17 dB  20 WPM  CQ      2007Z",
    "title": "RBN spot N1RWJ (7.039 CW)",
    "source": "rbn",
    "state": "US_RI",
    "qsl": "eqsl,lotw",
    "dxcc": 291,
    "entity": "United States of America",
    "cq": "5",
    "continent": "NA",
    "homeDxcc": 291,
    "homeEntity": "United States of America",
    "spotterDxcc": 291,
    "spotterEntity": "United States of America",
    "spotterCq": "5",
    "spotterContinent": "NA",
    "triggerComment": "EDH Discord",
    "received_at": "2026-06-20T20:07:35.850062Z"
  },
  {
    "fullCallsign": "KB9VBR",
    "callsign": "KB9VBR",
    "frequency": "7.227",
    "band": "40m",
    "mode": "ssb",
    "modeDetail": "ssb",
    "time": "19:39",
    "spotter": "KB9VBR",
    "rawText": "19:39 KB9VBR in US-12621 (Whitcomb Creek State Fish and Wildlife Area) 7.2270 SSB: Qrp",
    "title": "POTA KB9VBR in US-12621 (7.2270 SSB)",
    "comment": "Qrp",
    "source": "pota",
    "state": [
      "US_WI"
    ],
    "spotterState": "US_WI",
    "wwffRef": "US-12621",
    "wwffDivision": "US",
    "wwffName": "Whitcomb Creek State Fish and Wildlife Area",
    "qsl": "eqsl",
    "dxcc": 291,
    "entity": "United States of America",
    "cq": "4",
    "continent": "NA",
    "homeDxcc": 291,
    "homeEntity": "United States of America",
    "spotterDxcc": 291,
    "spotterEntity": "United States of America",
    "spotterCq": "4",
    "spotterContinent": "NA",
    "triggerComment": "YouTube",
    "received_at": "2026-06-20T19:39:44.352229Z"
  },
  {
    "fullCallsign": "KB9VBR",
    "callsign": "KB9VBR",
    "frequency": "18.146",
    "band": "17m",
    "mode": "ssb",
    "modeDetail": "ssb",
    "time": "19:16",
    "spotter": "KB9VBR",
    "rawText": "19:16 KB9VBR in US-12621 (Whitcomb Creek State Fish and Wildlife Area) 18.1460 SSB: Qrp",
    "title": "POTA KB9VBR in US-12621 (18.1460 SSB)",
    "comment": "Qrp",
    "source": "pota",
    "state": [
      "US_WI"
    ],
    "spotterState": "US_WI",
    "wwffRef": "US-12621",
    "wwffDivision": "US",
    "wwffName": "Whitcomb Creek State Fish and Wildlife Area",
    "qsl": "eqsl",
    "dxcc": 291,
    "entity": "United States of America",
    "cq": "4",
    "continent": "NA",
    "homeDxcc": 291,
    "homeEntity": "United States of America",
    "spotterDxcc": 291,
    "spotterEntity": "United States of America",
    "spotterCq": "4",
    "spotterContinent": "NA",
    "triggerComment": "YouTube",
    "received_at": "2026-06-20T19:17:41.868564Z"
  },
  {
    "fullCallsign": "KB9VBR",
    "callsign": "KB9VBR",
    "frequency": "14.309",
    "band": "20m",
    "mode": "ssb",
    "modeDetail": "ssb",
    "time": "19:13",
    "spotter": "KB9VBR",
    "rawText": "19:13 KB9VBR in US-12621 (Whitcomb Creek State Fish and Wildlife Area) 14.3090 SSB: Qrp",
    "title": "POTA KB9VBR in US-12621 (14.3090 SSB)",
    "comment": "Qrp",
    "source": "pota",
    "state": [
      "US_WI"
    ],
    "spotterState": "US_WI",
    "wwffRef": "US-12621",
    "wwffDivision": "US",
    "wwffName": "Whitcomb Creek State Fish and Wildlife Area",
    "qsl": "eqsl",
    "dxcc": 291,
    "entity": "United States of America",
    "cq": "4",
    "continent": "NA",
    "homeDxcc": 291,
    "homeEntity": "United States of America",
    "spotterDxcc": 291,
    "spotterEntity": "United States of America",
    "spotterCq": "4",
    "spotterContinent": "NA",
    "triggerComment": "YouTube",
    "received_at": "2026-06-20T19:13:41.140511Z"
  },
  {
    "fullCallsign": "KB9VBR",
    "callsign": "KB9VBR",
    "frequency": "14.309",
    "band": "20m",
    "mode": "ssb",
    "modeDetail": "ssb",
    "time": "18:59",
    "spotter": "KB9VBR",
    "rawText": "18:59 KB9VBR in US-12621 (Whitcomb Creek State Fish and Wildlife Area) 14.3090: Qrp",
    "title": "POTA KB9VBR in US-12621 (14.3090)",
    "comment": "Qrp",
    "source": "pota",
    "state": [
      "US_WI"
    ],
    "spotterState": "US_WI",
    "wwffRef": "US-12621",
    "wwffDivision": "US",
    "wwffName": "Whitcomb Creek State Fish and Wildlife Area",
    "qsl": "eqsl",
    "dxcc": 291,
    "entity": "United States of America",
    "cq": "4",
    "continent": "NA",
    "homeDxcc": 291,
    "homeEntity": "United States of America",
    "spotterDxcc": 291,
    "spotterEntity": "United States of America",
    "spotterCq": "4",
    "spotterContinent": "NA",
    "triggerComment": "YouTube",
    "received_at": "2026-06-20T18:59:43.099886Z"
  },
  {
    "fullCallsign": "N1RWJ",
    "callsign": "N1RWJ",
    "frequency": "14.0619",
    "band": "20m",
    "mode": "cw",
    "modeDetail": "cw",
    "time": "18:43",
    "spotter": "K9IMM",
    "snr": 3,
    "speed": 18,
    "rawText": "DX de K9IMM-#:  14061.90  N1RWJ          CW     3 dB  18 WPM  CQ      1843Z",
    "title": "RBN spot N1RWJ (14.0619 CW)",
    "source": "rbn",
    "state": "US_RI",
    "spotterState": "US_WI",
    "qsl": "eqsl,lotw",
    "dxcc": 291,
    "entity": "United States of America",
    "cq": "5",
    "continent": "NA",
    "homeDxcc": 291,
    "homeEntity": "United States of America",
    "spotterDxcc": 291,
    "spotterEntity": "United States of America",
    "spotterCq": "4",
    "spotterContinent": "NA",
    "triggerComment": "EDH Discord",
    "received_at": "2026-06-20T18:43:42.035964Z"
  },
  {
    "fullCallsign": "N1RWJ",
    "callsign": "N1RWJ",
    "frequency": "14.049",
    "band": "20m",
    "mode": "cw",
    "modeDetail": "cw",
    "time": "18:32",
    "spotter": "N1RWJ",
    "rawText": "18:32 N1RWJ in US-0512 (John Heinz National Wildlife Refuge) 14.0490 CW",
    "title": "POTA N1RWJ in US-0512 (14.0490 CW)",
    "comment": "",
    "source": "pota",
    "state": [
      "US_PA"
    ],
    "spotterState": "US_RI",
    "wwffRef": "US-0512",
    "wwffDivision": "US",
    "wwffName": "John Heinz National Wildlife Refuge",
    "qsl": "eqsl,lotw",
    "dxcc": 291,
    "entity": "United States of America",
    "cq": "5",
    "continent": "NA",
    "homeDxcc": 291,
    "homeEntity": "United States of America",
    "spotterDxcc": 291,
    "spotterEntity": "United States of America",
    "spotterCq": "5",
    "spotterContinent": "NA",
    "triggerComment": "EDH Discord",
    "received_at": "2026-06-20T18:32:41.200129Z"
  },
  {
    "fullCallsign": "N1RWJ",
    "callsign": "N1RWJ",
    "frequency": "14.0594",
    "band": "20m",
    "mode": "cw",
    "modeDetail": "cw",
    "time": "18:15",
    "spotter": "KM3T-5",
    "snr": 8,
    "speed": 17,
    "rawText": "DX de KM3T-5-#: 14059.40  N1RWJ          CW     8 dB  17 WPM  CQ      1815Z",
    "title": "RBN spot N1RWJ (14.0594 CW)",
    "source": "rbn",
    "state": "US_RI",
    "qsl": "eqsl,lotw",
    "dxcc": 291,
    "entity": "United States of America",
    "cq": "5",
    "continent": "NA",
    "homeDxcc": 291,
    "homeEntity": "United States of America",
    "spotterDxcc": 291,
    "spotterEntity": "United States of America",
    "spotterCq": "5",
    "spotterContinent": "NA",
    "triggerComment": "EDH Discord",
    "received_at": "2026-06-20T18:15:02.949214Z"
  },
  {
    "fullCallsign": "N1RWJ",
    "callsign": "N1RWJ",
    "frequency": "14.0595",
    "band": "20m",
    "mode": "cw",
    "modeDetail": "cw",
    "time": "18:04",
    "spotter": "W1NT-2",
    "snr": 28,
    "speed": 21,
    "rawText": "DX de W1NT-2-#: 14059.50  N1RWJ          CW    28 dB  21 WPM  CQ      1804Z",
    "title": "RBN spot N1RWJ (14.0595 CW)",
    "source": "rbn",
    "state": "US_RI",
    "qsl": "eqsl,lotw",
    "dxcc": 291,
    "entity": "United States of America",
    "cq": "5",
    "continent": "NA",
    "homeDxcc": 291,
    "homeEntity": "United States of America",
    "spotterDxcc": 291,
    "spotterEntity": "United States of America",
    "spotterCq": "5",
    "spotterContinent": "NA",
    "triggerComment": "EDH Discord",
    "received_at": "2026-06-20T18:04:24.095142Z"
  },
  {
    "fullCallsign": "N1RWJ",
    "callsign": "N1RWJ",
    "frequency": "14.0595",
    "band": "20m",
    "mode": "cw",
    "modeDetail": "cw",
    "time": "17:54",
    "spotter": "W1NT-2",
    "snr": 14,
    "speed": 21,
    "rawText": "DX de W1NT-2-#: 14059.50  N1RWJ          CW    14 dB  21 WPM  CQ      1754Z",
    "title": "RBN spot N1RWJ (14.0595 CW)",
    "source": "rbn",
    "state": "US_RI",
    "qsl": "eqsl,lotw",
    "dxcc": 291,
    "entity": "United States of America",
    "cq": "5",
    "continent": "NA",
    "homeDxcc": 291,
    "homeEntity": "United States of America",
    "spotterDxcc": 291,
    "spotterEntity": "United States of America",
    "spotterCq": "5",
    "spotterContinent": "NA",
    "triggerComment": "EDH Discord",
    "received_at": "2026-06-20T17:54:21.357722Z"
  },
  {
    "fullCallsign": "N1RWJ",
    "callsign": "N1RWJ",
    "frequency": "14.0579",
    "band": "20m",
    "mode": "cw",
    "modeDetail": "cw",
    "time": "17:49",
    "spotter": "WE9V",
    "snr": 3,
    "speed": 21,
    "rawText": "DX de WE9V-#:   14057.90  N1RWJ          CW     3 dB  21 WPM  CQ      1749Z",
    "title": "RBN spot N1RWJ (14.0579 CW)",
    "source": "rbn",
    "state": "US_RI",
    "spotterState": "US_WI",
    "qsl": "eqsl,lotw",
    "dxcc": 291,
    "entity": "United States of America",
    "cq": "5",
    "continent": "NA",
    "homeDxcc": 291,
    "homeEntity": "United States of America",
    "spotterDxcc": 291,
    "spotterEntity": "United States of America",
    "spotterCq": "4",
    "spotterContinent": "NA",
    "triggerComment": "EDH Discord",
    "received_at": "2026-06-20T17:49:43.935812Z"
  },
  {
    "fullCallsign": "N1RWJ",
    "callsign": "N1RWJ",
    "frequency": "14.0584",
    "band": "20m",
    "mode": "cw",
    "modeDetail": "cw",
    "time": "17:36",
    "spotter": "WB6BEE",
    "snr": 14,
    "speed": 20,
    "rawText": "DX de WB6BEE-#: 14058.40  N1RWJ          CW    14 dB  20 WPM  CQ      1736Z",
    "title": "RBN spot N1RWJ (14.0584 CW)",
    "source": "rbn",
    "state": "US_RI",
    "spotterState": "US_VA",
    "qsl": "eqsl,lotw",
    "dxcc": 291,
    "entity": "United States of America",
    "cq": "5",
    "continent": "NA",
    "homeDxcc": 291,
    "homeEntity": "United States of America",
    "spotterDxcc": 291,
    "spotterEntity": "United States of America",
    "spotterCq": "5",
    "spotterContinent": "NA",
    "triggerComment": "EDH Discord",
    "received_at": "2026-06-20T17:36:04.247402Z"
  },
  {
    "fullCallsign": "N1RWJ",
    "callsign": "N1RWJ",
    "frequency": "14.0584",
    "band": "20m",
    "mode": "cw",
    "modeDetail": "cw",
    "time": "17:26",
    "spotter": "KO4BHX",
    "snr": 19,
    "speed": 20,
    "rawText": "DX de KO4BHX-#: 14058.40  N1RWJ          CW    19 dB  20 WPM  CQ      1726Z",
    "title": "RBN spot N1RWJ (14.0584 CW)",
    "source": "rbn",
    "state": "US_RI",
    "spotterState": "US_NC",
    "qsl": "eqsl,lotw",
    "dxcc": 291,
    "entity": "United States of America",
    "cq": "5",
    "continent": "NA",
    "homeDxcc": 291,
    "homeEntity": "United States of America",
    "spotterDxcc": 291,
    "spotterEntity": "United States of America",
    "spotterCq": "5",
    "spotterContinent": "NA",
    "triggerComment": "EDH Discord",
    "received_at": "2026-06-20T17:26:01.820878Z"
  },
  {
    "fullCallsign": "N1RWJ",
    "callsign": "N1RWJ",
    "frequency": "14.278",
    "band": "20m",
    "mode": "ssb",
    "modeDetail": "ssb",
    "time": "14:40",
    "spotter": "N1RWJ",
    "rawText": "14:40 N1RWJ in US-1611 (Cheesequake State Park) 14.2780 SSB: QRT",
    "title": "POTA N1RWJ in US-1611 (14.2780 SSB)",
    "comment": "QRT",
    "source": "pota",
    "state": [
      "US_NJ"
    ],
    "spotterState": "US_RI",
    "wwffRef": "US-1611",
    "wwffDivision": "US",
    "wwffName": "Cheesequake State Park",
    "qsl": "eqsl,lotw",
    "dxcc": 291,
    "entity": "United States of America",
    "cq": "5",
    "continent": "NA",
    "homeDxcc": 291,
    "homeEntity": "United States of America",
    "spotterDxcc": 291,
    "spotterEntity": "United States of America",
    "spotterCq": "5",
    "spotterContinent": "NA",
    "triggerComment": "EDH Discord",
    "received_at": "2026-06-20T14:41:38.550971Z"
  },
  {
    "fullCallsign": "N8JRD",
    "callsign": "N8JRD",
    "frequency": "14.075426",
    "band": "20m",
    "mode": "ft8",
    "modeDetail": "ft8",
    "time": "14:19",
    "spotter": "DL8LAS",
    "snr": -15,
    "rawText": "DX de DL8LAS: 14075.4 N8JRD FT8 -15 dB 1419Z (STEMlab SDR FT8 TRX 1.0)",
    "title": "PSK Reporter spot N8JRD (14.075426 FT8)",
    "source": "pskreporter",
    "state": "US_MI",
    "qsl": "lotw",
    "dxcc": 291,
    "entity": "United States of America",
    "cq": "4",
    "continent": "NA",
    "homeDxcc": 291,
    "homeEntity": "United States of America",
    "spotterDxcc": 230,
    "spotterEntity": "Federal Republic of Germany",
    "spotterCq": "14",
    "spotterContinent": "EU",
    "triggerComment": "Everyday Ham",
    "received_at": "2026-06-20T14:24:50.706257Z"
  },
  {
    "fullCallsign": "N1RWJ",
    "callsign": "N1RWJ",
    "frequency": "14.061",
    "band": "20m",
    "mode": "cw",
    "modeDetail": "cw",
    "time": "14:22",
    "spotter": "AA4PA",
    "snr": 6,
    "speed": 20,
    "rawText": "DX de AA4PA-#:  14061.00  N1RWJ          CW     6 dB  20 WPM  CQ      1422Z",
    "title": "RBN spot N1RWJ (14.061 CW)",
    "source": "rbn",
    "state": "US_RI",
    "spotterState": "US_TN",
    "qsl": "eqsl,lotw",
    "dxcc": 291,
    "entity": "United States of America",
    "cq": "5",
    "continent": "NA",
    "homeDxcc": 291,
    "homeEntity": "United States of America",
    "spotterDxcc": 291,
    "spotterEntity": "United States of America",
    "spotterCq": "4",
    "spotterContinent": "NA",
    "triggerComment": "EDH Discord",
    "received_at": "2026-06-20T14:22:40.256089Z"
  },
  {
    "fullCallsign": "N8JRD",
    "callsign": "N8JRD",
    "frequency": "14.075357",
    "band": "20m",
    "mode": "ft8",
    "modeDetail": "ft8",
    "time": "14:13",
    "spotter": "N1GDD",
    "snr": -12,
    "rawText": "DX de N1GDD: 14075.4 N8JRD FT8 -12 dB 1413Z (WSJT-X v3.0.1)",
    "title": "PSK Reporter spot N8JRD (14.075357 FT8)",
    "source": "pskreporter",
    "state": "US_MI",
    "spotterState": "US_NH",
    "qsl": "lotw",
    "dxcc": 291,
    "entity": "United States of America",
    "cq": "4",
    "continent": "NA",
    "homeDxcc": 291,
    "homeEntity": "United States of America",
    "spotterDxcc": 291,
    "spotterEntity": "United States of America",
    "spotterCq": "5",
    "spotterContinent": "NA",
    "triggerComment": "Everyday Ham",
    "received_at": "2026-06-20T14:13:47.685737Z"
  },
  {
    "fullCallsign": "N1RWJ",
    "callsign": "N1RWJ",
    "frequency": "14.061",
    "band": "20m",
    "mode": "cw",
    "modeDetail": "cw",
    "time": "14:11",
    "spotter": "AA4PA",
    "snr": 8,
    "speed": 20,
    "rawText": "DX de AA4PA-#:  14061.00  N1RWJ          CW     8 dB  20 WPM  CQ      1411Z",
    "title": "RBN spot N1RWJ (14.061 CW)",
    "source": "rbn",
    "state": "US_RI",
    "spotterState": "US_TN",
    "qsl": "eqsl,lotw",
    "dxcc": 291,
    "entity": "United States of America",
    "cq": "5",
    "continent": "NA",
    "homeDxcc": 291,
    "homeEntity": "United States of America",
    "spotterDxcc": 291,
    "spotterEntity": "United States of America",
    "spotterCq": "4",
    "spotterContinent": "NA",
    "triggerComment": "EDH Discord",
    "received_at": "2026-06-20T14:11:24.450124Z"
  },
  {
    "fullCallsign": "N1RWJ",
    "callsign": "N1RWJ",
    "frequency": "7.039",
    "band": "40m",
    "mode": "cw",
    "modeDetail": "cw",
    "time": "13:57",
    "spotter": "KM3T-3",
    "snr": 17,
    "speed": 20,
    "rawText": "DX de KM3T-3-#:  7039.00  N1RWJ          CW    17 dB  20 WPM  CQ      1357Z",
    "title": "RBN spot N1RWJ (7.039 CW)",
    "source": "rbn",
    "state": "US_RI",
    "qsl": "eqsl,lotw",
    "dxcc": 291,
    "entity": "United States of America",
    "cq": "5",
    "continent": "NA",
    "homeDxcc": 291,
    "homeEntity": "United States of America",
    "spotterDxcc": 291,
    "spotterEntity": "United States of America",
    "spotterCq": "5",
    "spotterContinent": "NA",
    "triggerComment": "EDH Discord",
    "received_at": "2026-06-20T13:57:17.895084Z"
  },
  {
    "fullCallsign": "N1RWJ",
    "callsign": "N1RWJ",
    "frequency": "7.039",
    "band": "40m",
    "mode": "cw",
    "modeDetail": "cw",
    "time": "13:47",
    "spotter": "K9LC",
    "snr": 12,
    "speed": 20,
    "rawText": "DX de K9LC-#:    7039.00  N1RWJ          CW    12 dB  20 WPM  CQ      1347Z",
    "title": "RBN spot N1RWJ (7.039 CW)",
    "source": "rbn",
    "state": "US_RI",
    "spotterState": "US_IL",
    "qsl": "eqsl,lotw",
    "dxcc": 291,
    "entity": "United States of America",
    "cq": "5",
    "continent": "NA",
    "homeDxcc": 291,
    "homeEntity": "United States of America",
    "spotterDxcc": 291,
    "spotterEntity": "United States of America",
    "spotterCq": "4",
    "spotterContinent": "NA",
    "triggerComment": "EDH Discord",
    "received_at": "2026-06-20T13:47:05.504428Z"
  },
  {
    "fullCallsign": "N1RWJ",
    "callsign": "N1RWJ",
    "frequency": "14.053",
    "band": "20m",
    "mode": "cw",
    "modeDetail": "cw",
    "time": "00:28",
    "spotter": "OK1FCJ",
    "rawText": "00:28 N1RWJ in US-2149 (Tallman Mountain State Park) 14.0530 CW: RBN 5 dB 20 WPM via OK1FCJ-#",
    "title": "POTA N1RWJ in US-2149 (14.0530 CW)",
    "comment": "RBN 5 dB 20 WPM via OK1FCJ-#",
    "source": "pota",
    "state": [
      "US_NY"
    ],
    "wwffRef": "US-2149",
    "wwffDivision": "US",
    "wwffName": "Tallman Mountain State Park",
    "qsl": "eqsl,lotw",
    "dxcc": 291,
    "entity": "United States of America",
    "cq": "5",
    "continent": "NA",
    "homeDxcc": 291,
    "homeEntity": "United States of America",
    "spotterDxcc": 503,
    "spotterEntity": "Czech Republic",
    "spotterCq": "15",
    "spotterContinent": "EU",
    "triggerComment": "EDH Discord",
    "received_at": "2026-06-20T00:28:32.626412Z"
  },
  {
    "fullCallsign": "N8JRD",
    "callsign": "N8JRD",
    "frequency": "14.074",
    "band": "20m",
    "mode": "ft8",
    "modeDetail": "ft8",
    "time": "00:20",
    "spotter": "DR4W",
    "snr": -4,
    "rawText": "DX de DR4W-#:   14074.00  N8JRD          FT8   -4 dB          CQ      0020Z",
    "title": "RBN spot N8JRD (14.074 FT8)",
    "source": "rbn",
    "state": "US_MI",
    "qsl": "lotw",
    "dxcc": 291,
    "entity": "United States of America",
    "cq": "4",
    "continent": "NA",
    "homeDxcc": 291,
    "homeEntity": "United States of America",
    "spotterDxcc": 230,
    "spotterEntity": "Federal Republic of Germany",
    "spotterCq": "14",
    "spotterContinent": "EU",
    "triggerComment": "Everyday Ham",
    "received_at": "2026-06-20T00:20:23.275195Z"
  },
  {
    "fullCallsign": "N1RWJ",
    "callsign": "N1RWJ",
    "frequency": "14.053",
    "band": "20m",
    "mode": "cw",
    "modeDetail": "cw",
    "time": "00:18",
    "spotter": "N1RWJ",
    "rawText": "00:18 N1RWJ in US-2149 (Tallman Mountain State Park) 14.0530 CW",
    "title": "POTA N1RWJ in US-2149 (14.0530 CW)",
    "comment": "",
    "source": "pota",
    "state": [
      "US_NY"
    ],
    "spotterState": "US_RI",
    "wwffRef": "US-2149",
    "wwffDivision": "US",
    "wwffName": "Tallman Mountain State Park",
    "qsl": "eqsl,lotw",
    "dxcc": 291,
    "entity": "United States of America",
    "cq": "5",
    "continent": "NA",
    "homeDxcc": 291,
    "homeEntity": "United States of America",
    "spotterDxcc": 291,
    "spotterEntity": "United States of America",
    "spotterCq": "5",
    "spotterContinent": "NA",
    "triggerComment": "EDH Discord",
    "received_at": "2026-06-20T00:18:32.459349Z"
  },
  {
    "fullCallsign": "N1RWJ",
    "callsign": "N1RWJ",
    "frequency": "14.314",
    "band": "20m",
    "mode": "ssb",
    "modeDetail": "ssb",
    "time": "00:10",
    "spotter": "N1RWJ",
    "rawText": "00:10 N1RWJ in US-2149 (Tallman Mountain State Park) 14.3140 SSB",
    "title": "POTA N1RWJ in US-2149 (14.3140 SSB)",
    "comment": "",
    "source": "pota",
    "state": [
      "US_NY"
    ],
    "spotterState": "US_RI",
    "wwffRef": "US-2149",
    "wwffDivision": "US",
    "wwffName": "Tallman Mountain State Park",
    "qsl": "eqsl,lotw",
    "dxcc": 291,
    "entity": "United States of America",
    "cq": "5",
    "continent": "NA",
    "homeDxcc": 291,
    "homeEntity": "United States of America",
    "spotterDxcc": 291,
    "spotterEntity": "United States of America",
    "spotterCq": "5",
    "spotterContinent": "NA",
    "triggerComment": "EDH Discord",
    "received_at": "2026-06-20T00:11:32.506328Z"
  },
  {
    "fullCallsign": "N1RWJ",
    "callsign": "N1RWJ",
    "frequency": "14.314",
    "band": "20m",
    "mode": "ssb",
    "modeDetail": "ssb",
    "time": "23:56",
    "spotter": "N1RWJ",
    "rawText": "23:56 N1RWJ in US-2149 (Tallman Mountain State Park) 14.3140 SSB: QSY",
    "title": "POTA N1RWJ in US-2149 (14.3140 SSB)",
    "comment": "QSY",
    "source": "pota",
    "state": [
      "US_NY"
    ],
    "spotterState": "US_RI",
    "wwffRef": "US-2149",
    "wwffDivision": "US",
    "wwffName": "Tallman Mountain State Park",
    "qsl": "eqsl,lotw",
    "dxcc": 291,
    "entity": "United States of America",
    "cq": "5",
    "continent": "NA",
    "homeDxcc": 291,
    "homeEntity": "United States of America",
    "spotterDxcc": 291,
    "spotterEntity": "United States of America",
    "spotterCq": "5",
    "spotterContinent": "NA",
    "triggerComment": "EDH Discord",
    "received_at": "2026-06-19T23:56:32.320764Z"
  },
  {
    "fullCallsign": "N1RWJ",
    "callsign": "N1RWJ",
    "frequency": "14.0505",
    "band": "20m",
    "mode": "cw",
    "modeDetail": "cw",
    "time": "23:50",
    "spotter": "DL8LAS",
    "rawText": "23:50 N1RWJ in US-2149 (Tallman Mountain State Park) 14.0505 CW: RBN 12 dB 19 WPM via DL8LAS-#",
    "title": "POTA N1RWJ in US-2149 (14.0505 CW)",
    "comment": "RBN 12 dB 19 WPM via DL8LAS-#",
    "source": "pota",
    "state": [
      "US_NY"
    ],
    "wwffRef": "US-2149",
    "wwffDivision": "US",
    "wwffName": "Tallman Mountain State Park",
    "qsl": "eqsl,lotw",
    "dxcc": 291,
    "entity": "United States of America",
    "cq": "5",
    "continent": "NA",
    "homeDxcc": 291,
    "homeEntity": "United States of America",
    "spotterDxcc": 230,
    "spotterEntity": "Federal Republic of Germany",
    "spotterCq": "14",
    "spotterContinent": "EU",
    "triggerComment": "EDH Discord",
    "received_at": "2026-06-19T23:50:32.185503Z"
  },
  {
    "fullCallsign": "N1RWJ",
    "callsign": "N1RWJ",
    "frequency": "14.0505",
    "band": "20m",
    "mode": "cw",
    "modeDetail": "cw",
    "time": "23:30",
    "spotter": "HA2NA",
    "rawText": "23:30 N1RWJ in US-2149 (Tallman Mountain State Park) 14.0505 CW: RBN 9 dB 20 WPM via HA2NA-#",
    "title": "POTA N1RWJ in US-2149 (14.0505 CW)",
    "comment": "RBN 9 dB 20 WPM via HA2NA-#",
    "source": "pota",
    "state": [
      "US_NY"
    ],
    "wwffRef": "US-2149",
    "wwffDivision": "US",
    "wwffName": "Tallman Mountain State Park",
    "qsl": "eqsl,lotw",
    "dxcc": 291,
    "entity": "United States of America",
    "cq": "5",
    "continent": "NA",
    "homeDxcc": 291,
    "homeEntity": "United States of America",
    "spotterDxcc": 239,
    "spotterEntity": "Hungary",
    "spotterCq": "15",
    "spotterContinent": "EU",
    "triggerComment": "EDH Discord",
    "received_at": "2026-06-19T23:30:32.155455Z"
  },
  {
    "fullCallsign": "N1RWJ",
    "callsign": "N1RWJ",
    "frequency": "14.0505",
    "band": "20m",
    "mode": "cw",
    "modeDetail": "cw",
    "time": "23:19",
    "spotter": "KW7MM",
    "rawText": "23:19 N1RWJ in US-2149 (Tallman Mountain State Park) 14.0505 CW: RBN 29 dB 20 WPM via KW7MM-#",
    "title": "POTA N1RWJ in US-2149 (14.0505 CW)",
    "comment": "RBN 29 dB 20 WPM via KW7MM-#",
    "source": "pota",
    "state": [
      "US_NY"
    ],
    "spotterState": "US_AZ",
    "wwffRef": "US-2149",
    "wwffDivision": "US",
    "wwffName": "Tallman Mountain State Park",
    "qsl": "eqsl,lotw",
    "dxcc": 291,
    "entity": "United States of America",
    "cq": "5",
    "continent": "NA",
    "homeDxcc": 291,
    "homeEntity": "United States of America",
    "spotterDxcc": 291,
    "spotterEntity": "United States of America",
    "spotterCq": "3",
    "spotterContinent": "NA",
    "triggerComment": "EDH Discord",
    "received_at": "2026-06-19T23:20:32.153050Z"
  },
  {
    "fullCallsign": "N1RWJ",
    "callsign": "N1RWJ",
    "frequency": "14.0505",
    "band": "20m",
    "mode": "cw",
    "modeDetail": "cw",
    "time": "23:10",
    "spotter": "N1RWJ",
    "rawText": "23:10 N1RWJ in US-2149 (Tallman Mountain State Park) 14.0505 CW",
    "title": "POTA N1RWJ in US-2149 (14.0505 CW)",
    "comment": "",
    "source": "pota",
    "state": [
      "US_NY"
    ],
    "spotterState": "US_RI",
    "wwffRef": "US-2149",
    "wwffDivision": "US",
    "wwffName": "Tallman Mountain State Park",
    "qsl": "eqsl,lotw",
    "dxcc": 291,
    "entity": "United States of America",
    "cq": "5",
    "continent": "NA",
    "homeDxcc": 291,
    "homeEntity": "United States of America",
    "spotterDxcc": 291,
    "spotterEntity": "United States of America",
    "spotterCq": "5",
    "spotterContinent": "NA",
    "triggerComment": "EDH Discord",
    "received_at": "2026-06-19T23:10:34.272820Z"
  },
  {
    "fullCallsign": "KB9VBR",
    "callsign": "KB9VBR",
    "frequency": "14.278",
    "band": "20m",
    "mode": "ssb",
    "modeDetail": "ssb",
    "time": "19:43",
    "spotter": "K8WAG",
    "rawText": "19:43 KB9VBR in US-12029 (Alta State Fish and Wildlife Area) 14.2780 SSB: 55 OH",
    "title": "POTA KB9VBR in US-12029 (14.2780 SSB)",
    "comment": "55 OH",
    "source": "pota",
    "state": [
      "US_WI"
    ],
    "spotterState": "US_OH",
    "wwffRef": "US-12029",
    "wwffDivision": "US",
    "wwffName": "Alta State Fish and Wildlife Area",
    "qsl": "eqsl",
    "dxcc": 291,
    "entity": "United States of America",
    "cq": "4",
    "continent": "NA",
    "homeDxcc": 291,
    "homeEntity": "United States of America",
    "spotterDxcc": 291,
    "spotterEntity": "United States of America",
    "spotterCq": "4",
    "spotterContinent": "NA",
    "triggerComment": "YouTube",
    "received_at": "2026-06-19T19:43:49.689040Z"
  },
  {
    "fullCallsign": "KB9VBR",
    "callsign": "KB9VBR",
    "frequency": "14.278",
    "band": "20m",
    "mode": "ssb",
    "modeDetail": "ssb",
    "time": "19:31",
    "spotter": "KJ7VAD",
    "rawText": "19:31 KB9VBR in US-12029 (Alta State Fish and Wildlife Area) 14.2780 SSB: 51 Whidbey island, WA 73 :)",
    "title": "POTA KB9VBR in US-12029 (14.2780 SSB)",
    "comment": "51 Whidbey island, WA 73 :)",
    "source": "pota",
    "state": [
      "US_WI"
    ],
    "spotterState": "US_WA",
    "wwffRef": "US-12029",
    "wwffDivision": "US",
    "wwffName": "Alta State Fish and Wildlife Area",
    "qsl": "eqsl",
    "dxcc": 291,
    "entity": "United States of America",
    "cq": "4",
    "continent": "NA",
    "homeDxcc": 291,
    "homeEntity": "United States of America",
    "spotterDxcc": 291,
    "spotterEntity": "United States of America",
    "spotterCq": "3",
    "spotterContinent": "NA",
    "triggerComment": "YouTube",
    "received_at": "2026-06-19T19:32:00.219071Z"
  },
  {
    "fullCallsign": "KB9VBR",
    "callsign": "KB9VBR",
    "frequency": "14.278",
    "band": "20m",
    "mode": "ssb",
    "modeDetail": "ssb",
    "time": "19:11",
    "spotter": "WB9NDG",
    "rawText": "19:11 KB9VBR in US-12029 (Alta State Fish and Wildlife Area) 14.2780 SSB",
    "title": "POTA KB9VBR in US-12029 (14.2780 SSB)",
    "comment": "",
    "source": "pota",
    "state": [
      "US_WI"
    ],
    "spotterState": "US_FL",
    "wwffRef": "US-12029",
    "wwffDivision": "US",
    "wwffName": "Alta State Fish and Wildlife Area",
    "qsl": "eqsl",
    "dxcc": 291,
    "entity": "United States of America",
    "cq": "4",
    "continent": "NA",
    "homeDxcc": 291,
    "homeEntity": "United States of America",
    "spotterDxcc": 291,
    "spotterEntity": "United States of America",
    "spotterCq": "5",
    "spotterContinent": "NA",
    "triggerComment": "YouTube",
    "received_at": "2026-06-19T19:11:49.301624Z"
  },
  {
    "fullCallsign": "KB9VBR",
    "callsign": "KB9VBR",
    "frequency": "14.278",
    "band": "20m",
    "mode": "ssb",
    "modeDetail": "ssb",
    "time": "18:58",
    "spotter": "K1DLA",
    "rawText": "18:58 KB9VBR in US-12029 (Alta State Fish and Wildlife Area) 14.2780 SSB: 59 central Texas",
    "title": "POTA KB9VBR in US-12029 (14.2780 SSB)",
    "comment": "59 central Texas",
    "source": "pota",
    "state": [
      "US_WI"
    ],
    "spotterState": "US_TX",
    "wwffRef": "US-12029",
    "wwffDivision": "US",
    "wwffName": "Alta State Fish and Wildlife Area",
    "qsl": "eqsl",
    "dxcc": 291,
    "entity": "United States of America",
    "cq": "4",
    "continent": "NA",
    "homeDxcc": 291,
    "homeEntity": "United States of America",
    "spotterDxcc": 291,
    "spotterEntity": "United States of America",
    "spotterCq": "4",
    "spotterContinent": "NA",
    "triggerComment": "YouTube",
    "received_at": "2026-06-19T18:58:49.253932Z"
  },
  {
    "fullCallsign": "KB9VBR",
    "callsign": "KB9VBR",
    "frequency": "14.278",
    "band": "20m",
    "mode": "ssb",
    "modeDetail": "ssb",
    "time": "18:47",
    "spotter": "KB9VBR",
    "rawText": "18:47 KB9VBR in US-12029 (Alta State Fish and Wildlife Area) 14.2780 SSB",
    "title": "POTA KB9VBR in US-12029 (14.2780 SSB)",
    "comment": "",
    "source": "pota",
    "state": [
      "US_WI"
    ],
    "spotterState": "US_WI",
    "wwffRef": "US-12029",
    "wwffDivision": "US",
    "wwffName": "Alta State Fish and Wildlife Area",
    "qsl": "eqsl",
    "dxcc": 291,
    "entity": "United States of America",
    "cq": "4",
    "continent": "NA",
    "homeDxcc": 291,
    "homeEntity": "United States of America",
    "spotterDxcc": 291,
    "spotterEntity": "United States of America",
    "spotterCq": "4",
    "spotterContinent": "NA",
    "triggerComment": "YouTube",
    "received_at": "2026-06-19T18:47:52.859594Z"
  },
  {
    "fullCallsign": "KB9VBR",
    "callsign": "KB9VBR",
    "frequency": "14.261",
    "band": "20m",
    "mode": "ssb",
    "modeDetail": "ssb",
    "time": "18:43",
    "spotter": "KB9VBR",
    "rawText": "18:43 KB9VBR in US-12029 (Alta State Fish and Wildlife Area) 14.2610",
    "title": "POTA KB9VBR in US-12029 (14.2610)",
    "comment": "",
    "source": "pota",
    "state": [
      "US_WI"
    ],
    "spotterState": "US_WI",
    "wwffRef": "US-12029",
    "wwffDivision": "US",
    "wwffName": "Alta State Fish and Wildlife Area",
    "qsl": "eqsl",
    "dxcc": 291,
    "entity": "United States of America",
    "cq": "4",
    "continent": "NA",
    "homeDxcc": 291,
    "homeEntity": "United States of America",
    "spotterDxcc": 291,
    "spotterEntity": "United States of America",
    "spotterCq": "4",
    "spotterContinent": "NA",
    "triggerComment": "YouTube",
    "received_at": "2026-06-19T18:44:51.621261Z"
  },
  {
    "fullCallsign": "N1RWJ",
    "callsign": "N1RWJ",
    "frequency": "14.0505",
    "band": "20m",
    "mode": "cw",
    "modeDetail": "cw",
    "time": "17:31",
    "spotter": "KD7EFG",
    "snr": 18,
    "speed": 19,
    "rawText": "DX de KD7EFG-#: 14050.50  N1RWJ          CW    18 dB  19 WPM  CQ      1731Z",
    "title": "RBN spot N1RWJ (14.0505 CW)",
    "source": "rbn",
    "state": "US_RI",
    "spotterState": "US_UT",
    "qsl": "eqsl,lotw",
    "dxcc": 291,
    "entity": "United States of America",
    "cq": "5",
    "continent": "NA",
    "homeDxcc": 291,
    "homeEntity": "United States of America",
    "spotterDxcc": 291,
    "spotterEntity": "United States of America",
    "spotterCq": "3",
    "spotterContinent": "NA",
    "triggerComment": "EDH Discord",
    "received_at": "2026-06-19T17:31:59.741407Z"
  },
  {
    "fullCallsign": "N1RWJ",
    "callsign": "N1RWJ",
    "frequency": "14.0505",
    "band": "20m",
    "mode": "cw",
    "modeDetail": "cw",
    "time": "17:19",
    "spotter": "WE9V",
    "snr": 11,
    "speed": 20,
    "rawText": "DX de WE9V-#:   14050.50  N1RWJ          CW    11 dB  20 WPM  CQ      1719Z",
    "title": "RBN spot N1RWJ (14.0505 CW)",
    "source": "rbn",
    "state": "US_RI",
    "spotterState": "US_WI",
    "qsl": "eqsl,lotw",
    "dxcc": 291,
    "entity": "United States of America",
    "cq": "5",
    "continent": "NA",
    "homeDxcc": 291,
    "homeEntity": "United States of America",
    "spotterDxcc": 291,
    "spotterEntity": "United States of America",
    "spotterCq": "4",
    "spotterContinent": "NA",
    "triggerComment": "EDH Discord",
    "received_at": "2026-06-19T17:19:55.192834Z"
  },
  {
    "fullCallsign": "N1RWJ",
    "callsign": "N1RWJ",
    "frequency": "14.242",
    "band": "20m",
    "mode": "ssb",
    "modeDetail": "ssb",
    "time": "17:18",
    "spotter": "N1RWJ",
    "rawText": "17:18 N1RWJ in US-1716 (Silver Sands State Park) 14.2420 SSB",
    "title": "POTA N1RWJ in US-1716 (14.2420 SSB)",
    "comment": "",
    "source": "pota",
    "state": [
      "US_CT"
    ],
    "spotterState": "US_RI",
    "wwffRef": "US-1716",
    "wwffDivision": "US",
    "wwffName": "Silver Sands State Park",
    "qsl": "eqsl,lotw",
    "dxcc": 291,
    "entity": "United States of America",
    "cq": "5",
    "continent": "NA",
    "homeDxcc": 291,
    "homeEntity": "United States of America",
    "spotterDxcc": 291,
    "spotterEntity": "United States of America",
    "spotterCq": "5",
    "spotterContinent": "NA",
    "triggerComment": "EDH Discord",
    "received_at": "2026-06-19T17:18:48.011177Z"
  },
  {
    "fullCallsign": "N1RWJ",
    "callsign": "N1RWJ",
    "frequency": "14.242",
    "band": "20m",
    "mode": "ssb",
    "modeDetail": "ssb",
    "time": "17:08",
    "spotter": "N1RWJ",
    "rawText": "17:08 N1RWJ in US-1716 (Silver Sands State Park) 14.2420 SSB",
    "title": "POTA N1RWJ in US-1716 (14.2420 SSB)",
    "comment": "",
    "source": "pota",
    "state": [
      "US_CT"
    ],
    "spotterState": "US_RI",
    "wwffRef": "US-1716",
    "wwffDivision": "US",
    "wwffName": "Silver Sands State Park",
    "qsl": "eqsl,lotw",
    "dxcc": 291,
    "entity": "United States of America",
    "cq": "5",
    "continent": "NA",
    "homeDxcc": 291,
    "homeEntity": "United States of America",
    "spotterDxcc": 291,
    "spotterEntity": "United States of America",
    "spotterCq": "5",
    "spotterContinent": "NA",
    "triggerComment": "EDH Discord",
    "received_at": "2026-06-19T17:08:47.930667Z"
  },
  {
    "fullCallsign": "N1RWJ",
    "callsign": "N1RWJ",
    "frequency": "14.0505",
    "band": "20m",
    "mode": "cw",
    "modeDetail": "cw",
    "time": "17:03",
    "spotter": "WE9V",
    "snr": 13,
    "speed": 21,
    "rawText": "DX de WE9V-#:   14050.50  N1RWJ          CW    13 dB  21 WPM  CQ      1703Z",
    "title": "RBN spot N1RWJ (14.0505 CW)",
    "source": "rbn",
    "state": "US_RI",
    "spotterState": "US_WI",
    "qsl": "eqsl,lotw",
    "dxcc": 291,
    "entity": "United States of America",
    "cq": "5",
    "continent": "NA",
    "homeDxcc": 291,
    "homeEntity": "United States of America",
    "spotterDxcc": 291,
    "spotterEntity": "United States of America",
    "spotterCq": "4",
    "spotterContinent": "NA",
    "triggerComment": "EDH Discord",
    "received_at": "2026-06-19T17:03:51.013439Z"
  },
  {
    "fullCallsign": "N1RWJ",
    "callsign": "N1RWJ",
    "frequency": "14.0505",
    "band": "20m",
    "mode": "cw",
    "modeDetail": "cw",
    "time": "16:53",
    "spotter": "WE9V",
    "snr": 9,
    "speed": 19,
    "rawText": "DX de WE9V-#:   14050.50  N1RWJ          CW     9 dB  19 WPM  CQ      1653Z",
    "title": "RBN spot N1RWJ (14.0505 CW)",
    "source": "rbn",
    "state": "US_RI",
    "spotterState": "US_WI",
    "qsl": "eqsl,lotw",
    "dxcc": 291,
    "entity": "United States of America",
    "cq": "5",
    "continent": "NA",
    "homeDxcc": 291,
    "homeEntity": "United States of America",
    "spotterDxcc": 291,
    "spotterEntity": "United States of America",
    "spotterCq": "4",
    "spotterContinent": "NA",
    "triggerComment": "EDH Discord",
    "received_at": "2026-06-19T16:53:31.380447Z"
  },
  {
    "fullCallsign": "N1RWJ",
    "callsign": "N1RWJ",
    "frequency": "14.040",
    "band": "20m",
    "mode": "cw",
    "modeDetail": "cw",
    "time": "13:59",
    "spotter": "KC4YVA",
    "snr": 19,
    "speed": 20,
    "rawText": "DX de KC4YVA-#: 14040.00  N1RWJ          CW    19 dB  20 WPM  CQ      1359Z",
    "title": "RBN spot N1RWJ (14.040 CW)",
    "source": "rbn",
    "state": "US_RI",
    "spotterState": "US_VA",
    "qsl": "eqsl,lotw",
    "dxcc": 291,
    "entity": "United States of America",
    "cq": "5",
    "continent": "NA",
    "homeDxcc": 291,
    "homeEntity": "United States of America",
    "spotterDxcc": 291,
    "spotterEntity": "United States of America",
    "spotterCq": "5",
    "spotterContinent": "NA",
    "triggerComment": "EDH Discord",
    "received_at": "2026-06-19T13:59:05.561497Z"
  },
  {
    "fullCallsign": "N1RWJ",
    "callsign": "N1RWJ",
    "frequency": "14.040",
    "band": "20m",
    "mode": "cw",
    "modeDetail": "cw",
    "time": "13:48",
    "spotter": "N1RWJ",
    "rawText": "13:48 N1RWJ in US-6991 (Rockville Wildlife Management Area) 14.0400 CW",
    "title": "POTA N1RWJ in US-6991 (14.0400 CW)",
    "comment": "",
    "source": "pota",
    "state": [
      "US_RI"
    ],
    "spotterState": "US_RI",
    "wwffRef": "US-6991",
    "wwffDivision": "US",
    "wwffName": "Rockville Wildlife Management Area",
    "qsl": "eqsl,lotw",
    "dxcc": 291,
    "entity": "United States of America",
    "cq": "5",
    "continent": "NA",
    "homeDxcc": 291,
    "homeEntity": "United States of America",
    "spotterDxcc": 291,
    "spotterEntity": "United States of America",
    "spotterCq": "5",
    "spotterContinent": "NA",
    "triggerComment": "EDH Discord",
    "received_at": "2026-06-19T13:48:47.300372Z"
  },
  {
    "fullCallsign": "N1RWJ",
    "callsign": "N1RWJ",
    "frequency": "10.119",
    "band": "30m",
    "mode": "cw",
    "modeDetail": "cw",
    "time": "13:42",
    "spotter": "K1RA",
    "snr": 23,
    "speed": 19,
    "rawText": "DX de K1RA-#:   10119.00  N1RWJ          CW    23 dB  19 WPM  CQ      1342Z",
    "title": "RBN spot N1RWJ (10.119 CW)",
    "source": "rbn",
    "state": "US_RI",
    "spotterState": "US_VA",
    "qsl": "eqsl,lotw",
    "dxcc": 291,
    "entity": "United States of America",
    "cq": "5",
    "continent": "NA",
    "homeDxcc": 291,
    "homeEntity": "United States of America",
    "spotterDxcc": 291,
    "spotterEntity": "United States of America",
    "spotterCq": "5",
    "spotterContinent": "NA",
    "triggerComment": "EDH Discord",
    "received_at": "2026-06-19T13:42:10.407396Z"
  },
  {
    "fullCallsign": "N1RWJ",
    "callsign": "N1RWJ",
    "frequency": "7.037",
    "band": "40m",
    "mode": "cw",
    "modeDetail": "cw",
    "time": "13:37",
    "spotter": "W3UA",
    "rawText": "13:37 N1RWJ in US-6991 (Rockville Wildlife Management Area) 7.0370 CW: RBN 21 dB 20 WPM via W3UA-#",
    "title": "POTA N1RWJ in US-6991 (7.0370 CW)",
    "comment": "RBN 21 dB 20 WPM via W3UA-#",
    "source": "pota",
    "state": [
      "US_RI"
    ],
    "spotterState": "US_NH",
    "wwffRef": "US-6991",
    "wwffDivision": "US",
    "wwffName": "Rockville Wildlife Management Area",
    "qsl": "eqsl,lotw",
    "dxcc": 291,
    "entity": "United States of America",
    "cq": "5",
    "continent": "NA",
    "homeDxcc": 291,
    "homeEntity": "United States of America",
    "spotterDxcc": 291,
    "spotterEntity": "United States of America",
    "spotterCq": "5",
    "spotterContinent": "NA",
    "triggerComment": "EDH Discord",
    "received_at": "2026-06-19T13:37:46.976697Z"
  }
]