[
  {
    "fullCallsign": "W8KNX",
    "callsign": "W8KNX",
    "frequency": "21.074732",
    "band": "15m",
    "mode": "ft8",
    "modeDetail": "ft8",
    "time": "17:04",
    "spotter": "NG7M",
    "snr": -21,
    "rawText": "DX de NG7M: 21074.7 W8KNX FT8 -21 dB 1704Z (CWSL_DIGI 0.88)",
    "title": "PSK Reporter spot W8KNX (21.074732 FT8)",
    "source": "pskreporter",
    "state": "US_MI",
    "spotterState": "US_UT",
    "qsl": "eqsl,lotw",
    "dxcc": 291,
    "entity": "United States of America",
    "cq": "4",
    "continent": "NA",
    "homeDxcc": 291,
    "homeEntity": "United States of America",
    "spotterDxcc": 291,
    "spotterEntity": "United States of America",
    "spotterCq": "3",
    "spotterContinent": "NA",
    "triggerComment": "Everyday Ham",
    "received_at": "2026-06-07T17:04:56.068431Z"
  },
  {
    "fullCallsign": "W8KNX",
    "callsign": "W8KNX",
    "frequency": "7.074826",
    "band": "40m",
    "mode": "ft8",
    "modeDetail": "ft8",
    "time": "16:57",
    "spotter": "N8LI",
    "snr": -10,
    "rawText": "DX de N8LI: 7074.8 W8KNX FT8 -10 dB 1657Z (Red Pitaya FT8 TRX 1.0)",
    "title": "PSK Reporter spot W8KNX (7.074826 FT8)",
    "source": "pskreporter",
    "state": "US_MI",
    "spotterState": "US_RI",
    "qsl": "eqsl,lotw",
    "dxcc": 291,
    "entity": "United States of America",
    "cq": "4",
    "continent": "NA",
    "homeDxcc": 291,
    "homeEntity": "United States of America",
    "spotterDxcc": 291,
    "spotterEntity": "United States of America",
    "spotterCq": "5",
    "spotterContinent": "NA",
    "triggerComment": "Everyday Ham",
    "received_at": "2026-06-07T17:01:34.606011Z"
  },
  {
    "fullCallsign": "W8KNX",
    "callsign": "W8KNX",
    "frequency": "7.081313",
    "band": "40m",
    "mode": "ft8",
    "modeDetail": "ft8",
    "time": "16:51",
    "spotter": "WB5BHS",
    "snr": -14,
    "rawText": "DX de WB5BHS: 7081.3 W8KNX FT8 -14 dB 1651Z (WSJT-X v2.7.1-devel ial+)",
    "title": "PSK Reporter spot W8KNX (7.081313 FT8)",
    "source": "pskreporter",
    "state": "US_MI",
    "spotterState": "US_AR",
    "qsl": "eqsl,lotw",
    "dxcc": 291,
    "entity": "United States of America",
    "cq": "4",
    "continent": "NA",
    "homeDxcc": 291,
    "homeEntity": "United States of America",
    "spotterDxcc": 291,
    "spotterEntity": "United States of America",
    "spotterCq": "4",
    "spotterContinent": "NA",
    "triggerComment": "Everyday Ham",
    "received_at": "2026-06-07T16:52:54.351999Z"
  },
  {
    "fullCallsign": "W8KNX",
    "callsign": "W8KNX",
    "frequency": "7.074",
    "band": "40m",
    "mode": "ft8",
    "modeDetail": "ft8",
    "time": "16:51",
    "spotter": "WE9V",
    "snr": -3,
    "rawText": "DX de WE9V-#:    7074.00  W8KNX          FT8   -3 dB  EN74    CQ      1651Z",
    "title": "RBN spot W8KNX (7.074 FT8)",
    "source": "rbn",
    "state": "US_MI",
    "spotterState": "US_WI",
    "qsl": "eqsl,lotw",
    "dxcc": 291,
    "entity": "United States of America",
    "cq": "4",
    "continent": "NA",
    "homeDxcc": 291,
    "homeEntity": "United States of America",
    "spotterDxcc": 291,
    "spotterEntity": "United States of America",
    "spotterCq": "4",
    "spotterContinent": "NA",
    "triggerComment": "Everyday Ham",
    "received_at": "2026-06-07T16:51:34.483841Z"
  },
  {
    "fullCallsign": "N8JRD",
    "callsign": "N8JRD",
    "frequency": "14.075721",
    "band": "20m",
    "mode": "ft8",
    "modeDetail": "ft8",
    "time": "16:46",
    "spotter": "NG5P",
    "snr": -19,
    "rawText": "DX de NG5P: 14075.7 N8JRD FT8 -19 dB 1646Z (SparkSDR v2.0.992.0)",
    "title": "PSK Reporter spot N8JRD (14.075721 FT8)",
    "source": "pskreporter",
    "state": "US_MI",
    "spotterState": "US_AR",
    "qsl": "lotw",
    "dxcc": 291,
    "entity": "United States of America",
    "cq": "4",
    "continent": "NA",
    "homeDxcc": 291,
    "homeEntity": "United States of America",
    "spotterDxcc": 291,
    "spotterEntity": "United States of America",
    "spotterCq": "4",
    "spotterContinent": "NA",
    "triggerComment": "Everyday Ham",
    "received_at": "2026-06-07T16:50:46.999089Z"
  },
  {
    "fullCallsign": "N8JRD",
    "callsign": "N8JRD",
    "frequency": "14.074",
    "band": "20m",
    "mode": "ft8",
    "modeDetail": "ft8",
    "time": "16:36",
    "spotter": "WA7LNW",
    "snr": -11,
    "rawText": "DX de WA7LNW-#: 14074.00  N8JRD          FT8  -11 dB  EN74    CQ      1636Z",
    "title": "RBN spot N8JRD (14.074 FT8)",
    "source": "rbn",
    "state": "US_MI",
    "spotterState": "US_UT",
    "qsl": "lotw",
    "dxcc": 291,
    "entity": "United States of America",
    "cq": "4",
    "continent": "NA",
    "homeDxcc": 291,
    "homeEntity": "United States of America",
    "spotterDxcc": 291,
    "spotterEntity": "United States of America",
    "spotterCq": "3",
    "spotterContinent": "NA",
    "triggerComment": "Everyday Ham",
    "received_at": "2026-06-07T16:36:02.222253Z"
  },
  {
    "fullCallsign": "N8JRD",
    "callsign": "N8JRD",
    "frequency": "14.075714",
    "band": "20m",
    "mode": "ft8",
    "modeDetail": "ft8",
    "time": "16:20",
    "spotter": "WE6Z",
    "snr": -14,
    "rawText": "DX de WE6Z: 14075.7 N8JRD FT8 -14 dB 1620Z (SparkSDR v2.0.33.0)",
    "title": "PSK Reporter spot N8JRD (14.075714 FT8)",
    "source": "pskreporter",
    "state": "US_MI",
    "spotterState": "US_CA",
    "qsl": "lotw",
    "dxcc": 291,
    "entity": "United States of America",
    "cq": "4",
    "continent": "NA",
    "homeDxcc": 291,
    "homeEntity": "United States of America",
    "spotterDxcc": 291,
    "spotterEntity": "United States of America",
    "spotterCq": "3",
    "spotterContinent": "NA",
    "triggerComment": "Everyday Ham",
    "received_at": "2026-06-07T16:26:01.685049Z"
  },
  {
    "fullCallsign": "N8JRD",
    "callsign": "N8JRD",
    "frequency": "14.074",
    "band": "20m",
    "mode": "ft8",
    "modeDetail": "ft8",
    "time": "16:15",
    "spotter": "K1RA-4",
    "snr": -18,
    "rawText": "DX de K1RA-4-#: 14074.00  N8JRD          FT8  -18 dB  EN82    CQ      1615Z",
    "title": "RBN spot N8JRD (14.074 FT8)",
    "source": "rbn",
    "state": "US_MI",
    "qsl": "lotw",
    "dxcc": 291,
    "entity": "United States of America",
    "cq": "4",
    "continent": "NA",
    "homeDxcc": 291,
    "homeEntity": "United States of America",
    "spotterDxcc": 291,
    "spotterEntity": "United States of America",
    "spotterCq": "5",
    "spotterContinent": "NA",
    "triggerComment": "Everyday Ham",
    "received_at": "2026-06-07T16:15:57.022785Z"
  },
  {
    "fullCallsign": "N8JRD",
    "callsign": "N8JRD",
    "frequency": "14.256",
    "band": "20m",
    "mode": "ssb",
    "modeDetail": "ssb",
    "time": "15:26",
    "spotter": "N8JRD",
    "rawText": "15:26 N8JRD in US-1503 (Hartwick Pines State Park) 14.2560 SSB: Us1503",
    "title": "POTA N8JRD in US-1503 (14.2560 SSB)",
    "comment": "Us1503",
    "source": "pota",
    "state": [
      "US_MI"
    ],
    "spotterState": "US_MI",
    "wwffRef": "US-1503",
    "wwffDivision": "US",
    "wwffName": "Hartwick Pines State Park",
    "qsl": "lotw",
    "dxcc": 291,
    "entity": "United States of America",
    "cq": "4",
    "continent": "NA",
    "homeDxcc": 291,
    "homeEntity": "United States of America",
    "spotterDxcc": 291,
    "spotterEntity": "United States of America",
    "spotterCq": "4",
    "spotterContinent": "NA",
    "triggerComment": "Everyday Ham",
    "received_at": "2026-06-07T15:26:53.032149Z"
  },
  {
    "fullCallsign": "W8KNX",
    "callsign": "W8KNX",
    "frequency": "14.075196",
    "band": "20m",
    "mode": "ft8",
    "modeDetail": "ft8",
    "time": "15:20",
    "spotter": "KC1YFS",
    "snr": -20,
    "rawText": "DX de KC1YFS: 14075.2 W8KNX FT8 -20 dB 1520Z (OpenWebRX v1.2.115)",
    "title": "PSK Reporter spot W8KNX (14.075196 FT8)",
    "source": "pskreporter",
    "state": "US_MI",
    "spotterState": "US_RI",
    "qsl": "eqsl,lotw",
    "dxcc": 291,
    "entity": "United States of America",
    "cq": "4",
    "continent": "NA",
    "homeDxcc": 291,
    "homeEntity": "United States of America",
    "spotterDxcc": 291,
    "spotterEntity": "United States of America",
    "spotterCq": "5",
    "spotterContinent": "NA",
    "triggerComment": "Everyday Ham",
    "received_at": "2026-06-07T15:24:04.108537Z"
  },
  {
    "fullCallsign": "W8KNX",
    "callsign": "W8KNX",
    "frequency": "18.100",
    "band": "17m",
    "mode": "ft8",
    "modeDetail": "ft8",
    "time": "15:15",
    "spotter": "K1RA-4",
    "snr": -23,
    "rawText": "DX de K1RA-4-#: 18100.00  W8KNX          FT8  -23 dB  EN74    CQ      1515Z",
    "title": "RBN spot W8KNX (18.100 FT8)",
    "source": "rbn",
    "state": "US_MI",
    "qsl": "eqsl,lotw",
    "dxcc": 291,
    "entity": "United States of America",
    "cq": "4",
    "continent": "NA",
    "homeDxcc": 291,
    "homeEntity": "United States of America",
    "spotterDxcc": 291,
    "spotterEntity": "United States of America",
    "spotterCq": "5",
    "spotterContinent": "NA",
    "triggerComment": "Everyday Ham",
    "received_at": "2026-06-07T15:15:41.091324Z"
  },
  {
    "fullCallsign": "W8KNX",
    "callsign": "W8KNX",
    "frequency": "14.074738",
    "band": "20m",
    "mode": "ft8",
    "modeDetail": "ft8",
    "time": "15:09",
    "spotter": "W7XBC",
    "snr": -13,
    "rawText": "DX de W7XBC: 14074.7 W8KNX FT8 -13 dB 1509Z (web-888)",
    "title": "PSK Reporter spot W8KNX (14.074738 FT8)",
    "source": "pskreporter",
    "state": "US_MI",
    "spotterState": "US_NV",
    "qsl": "eqsl,lotw",
    "dxcc": 291,
    "entity": "United States of America",
    "cq": "4",
    "continent": "NA",
    "homeDxcc": 291,
    "homeEntity": "United States of America",
    "spotterDxcc": 291,
    "spotterEntity": "United States of America",
    "spotterCq": "3",
    "spotterContinent": "NA",
    "triggerComment": "Everyday Ham",
    "received_at": "2026-06-07T15:12:22.808616Z"
  },
  {
    "fullCallsign": "KB9VBR",
    "callsign": "KB9VBR",
    "frequency": "7.074",
    "band": "40m",
    "mode": "ft8",
    "modeDetail": "ft8",
    "time": "15:09",
    "spotter": "KB9VBR",
    "rawText": "15:09 KB9VBR in US-4354 (Point Beach State Forest) 7.0740 FT8: Qrt",
    "title": "POTA KB9VBR in US-4354 (7.0740 FT8)",
    "comment": "Qrt",
    "source": "pota",
    "state": [
      "US_WI"
    ],
    "spotterState": "US_WI",
    "wwffRef": "US-4354",
    "wwffDivision": "US",
    "wwffName": "Point Beach State Forest",
    "qsl": "eqsl",
    "dxcc": 291,
    "entity": "United States of America",
    "cq": "4",
    "continent": "NA",
    "homeDxcc": 291,
    "homeEntity": "United States of America",
    "spotterDxcc": 291,
    "spotterEntity": "United States of America",
    "spotterCq": "4",
    "spotterContinent": "NA",
    "triggerComment": "YouTube",
    "received_at": "2026-06-07T15:09:53.130567Z"
  },
  {
    "fullCallsign": "KB9VBR",
    "callsign": "KB9VBR",
    "frequency": "7.081418",
    "band": "40m",
    "mode": "ft8",
    "modeDetail": "ft8",
    "time": "15:04",
    "spotter": "WB5BHS",
    "snr": -11,
    "rawText": "DX de WB5BHS: 7081.4 KB9VBR FT8 -11 dB 1504Z (WSJT-X v2.7.1-devel ial+)",
    "title": "PSK Reporter spot KB9VBR (7.081418 FT8)",
    "source": "pskreporter",
    "state": "US_WI",
    "spotterState": "US_AR",
    "qsl": "eqsl",
    "dxcc": 291,
    "entity": "United States of America",
    "cq": "4",
    "continent": "NA",
    "homeDxcc": 291,
    "homeEntity": "United States of America",
    "spotterDxcc": 291,
    "spotterEntity": "United States of America",
    "spotterCq": "4",
    "spotterContinent": "NA",
    "triggerComment": "YouTube",
    "received_at": "2026-06-07T15:05:06.362891Z"
  },
  {
    "fullCallsign": "W8KNX",
    "callsign": "W8KNX",
    "frequency": "14.074831",
    "band": "20m",
    "mode": "ft8",
    "modeDetail": "ft8",
    "time": "15:01",
    "spotter": "K0MEZ",
    "snr": -23,
    "rawText": "DX de K0MEZ: 14074.8 W8KNX FT8 -23 dB 1501Z (WSJT-X v2.7.0 b4f9a4)",
    "title": "PSK Reporter spot W8KNX (14.074831 FT8)",
    "source": "pskreporter",
    "state": "US_MI",
    "spotterState": "US_MO",
    "qsl": "eqsl,lotw",
    "dxcc": 291,
    "entity": "United States of America",
    "cq": "4",
    "continent": "NA",
    "homeDxcc": 291,
    "homeEntity": "United States of America",
    "spotterDxcc": 291,
    "spotterEntity": "United States of America",
    "spotterCq": "4",
    "spotterContinent": "NA",
    "triggerComment": "Everyday Ham",
    "received_at": "2026-06-07T15:02:19.296561Z"
  },
  {
    "fullCallsign": "KB9VBR",
    "callsign": "KB9VBR",
    "frequency": "7.07485",
    "band": "40m",
    "mode": "ft8",
    "modeDetail": "ft8",
    "time": "14:59",
    "spotter": "K3GMQ",
    "snr": -14,
    "rawText": "DX de K3GMQ: 7074.8 KB9VBR FT8 -14 dB 1459Z (UberSDR 0.1.51)",
    "title": "PSK Reporter spot KB9VBR (7.07485 FT8)",
    "source": "pskreporter",
    "state": "US_WI",
    "spotterState": "US_PA",
    "qsl": "eqsl",
    "dxcc": 291,
    "entity": "United States of America",
    "cq": "4",
    "continent": "NA",
    "homeDxcc": 291,
    "homeEntity": "United States of America",
    "spotterDxcc": 291,
    "spotterEntity": "United States of America",
    "spotterCq": "5",
    "spotterContinent": "NA",
    "triggerComment": "YouTube",
    "received_at": "2026-06-07T14:59:36.286873Z"
  },
  {
    "fullCallsign": "KB9VBR",
    "callsign": "KB9VBR",
    "frequency": "7.074853",
    "band": "40m",
    "mode": "ft8",
    "modeDetail": "ft8",
    "time": "14:46",
    "spotter": "N0IGU",
    "snr": -2,
    "rawText": "DX de N0IGU: 7074.9 KB9VBR FT8 -2 dB 1446Z (WSJT-X v3.0.0 i+)",
    "title": "PSK Reporter spot KB9VBR (7.074853 FT8)",
    "source": "pskreporter",
    "state": "US_WI",
    "spotterState": "US_NE",
    "qsl": "eqsl",
    "dxcc": 291,
    "entity": "United States of America",
    "cq": "4",
    "continent": "NA",
    "homeDxcc": 291,
    "homeEntity": "United States of America",
    "spotterDxcc": 291,
    "spotterEntity": "United States of America",
    "spotterCq": "4",
    "spotterContinent": "NA",
    "triggerComment": "YouTube",
    "received_at": "2026-06-07T14:48:59.993228Z"
  },
  {
    "fullCallsign": "KB9VBR",
    "callsign": "KB9VBR",
    "frequency": "7.081417",
    "band": "40m",
    "mode": "ft8",
    "modeDetail": "ft8",
    "time": "14:40",
    "spotter": "WB5BHS",
    "snr": -13,
    "rawText": "DX de WB5BHS: 7081.4 KB9VBR FT8 -13 dB 1440Z (WSJT-X v2.7.1-devel ial+)",
    "title": "PSK Reporter spot KB9VBR (7.081417 FT8)",
    "source": "pskreporter",
    "state": "US_WI",
    "spotterState": "US_AR",
    "qsl": "eqsl",
    "dxcc": 291,
    "entity": "United States of America",
    "cq": "4",
    "continent": "NA",
    "homeDxcc": 291,
    "homeEntity": "United States of America",
    "spotterDxcc": 291,
    "spotterEntity": "United States of America",
    "spotterCq": "4",
    "spotterContinent": "NA",
    "triggerComment": "YouTube",
    "received_at": "2026-06-07T14:41:38.456120Z"
  },
  {
    "fullCallsign": "KB9VBR",
    "callsign": "KB9VBR",
    "frequency": "7.07486",
    "band": "40m",
    "mode": "ft8",
    "modeDetail": "ft8",
    "time": "14:38",
    "spotter": "VA3XAN",
    "snr": -7,
    "rawText": "DX de VA3XAN: 7074.9 KB9VBR FT8 -7 dB 1438Z (SmartSDR7.0.93)",
    "title": "PSK Reporter spot KB9VBR (7.07486 FT8)",
    "source": "pskreporter",
    "state": "US_WI",
    "spotterState": "CA_ON",
    "qsl": "eqsl",
    "dxcc": 291,
    "entity": "United States of America",
    "cq": "4",
    "continent": "NA",
    "homeDxcc": 291,
    "homeEntity": "United States of America",
    "spotterDxcc": 1,
    "spotterEntity": "Canada",
    "spotterCq": "4",
    "spotterContinent": "NA",
    "triggerComment": "YouTube",
    "received_at": "2026-06-07T14:38:54.130460Z"
  },
  {
    "fullCallsign": "KB9VBR",
    "callsign": "KB9VBR",
    "frequency": "7.074851",
    "band": "40m",
    "mode": "ft8",
    "modeDetail": "ft8",
    "time": "14:27",
    "spotter": "AE5AU",
    "snr": -16,
    "rawText": "DX de AE5AU: 7074.9 KB9VBR FT8 -16 dB 1427Z (SparkSDR v2.0.992.0)",
    "title": "PSK Reporter spot KB9VBR (7.074851 FT8)",
    "source": "pskreporter",
    "state": "US_WI",
    "spotterState": "US_AR",
    "qsl": "eqsl",
    "dxcc": 291,
    "entity": "United States of America",
    "cq": "4",
    "continent": "NA",
    "homeDxcc": 291,
    "homeEntity": "United States of America",
    "spotterDxcc": 291,
    "spotterEntity": "United States of America",
    "spotterCq": "4",
    "spotterContinent": "NA",
    "triggerComment": "YouTube",
    "received_at": "2026-06-07T14:28:51.863479Z"
  },
  {
    "fullCallsign": "KB9VBR",
    "callsign": "KB9VBR",
    "frequency": "7.081418",
    "band": "40m",
    "mode": "ft8",
    "modeDetail": "ft8",
    "time": "14:20",
    "spotter": "WB5BHS",
    "snr": -22,
    "rawText": "DX de WB5BHS: 7081.4 KB9VBR FT8 -22 dB 1420Z (WSJT-X v2.7.1-devel ial+)",
    "title": "PSK Reporter spot KB9VBR (7.081418 FT8)",
    "source": "pskreporter",
    "state": "US_WI",
    "spotterState": "US_AR",
    "qsl": "eqsl",
    "dxcc": 291,
    "entity": "United States of America",
    "cq": "4",
    "continent": "NA",
    "homeDxcc": 291,
    "homeEntity": "United States of America",
    "spotterDxcc": 291,
    "spotterEntity": "United States of America",
    "spotterCq": "4",
    "spotterContinent": "NA",
    "triggerComment": "YouTube",
    "received_at": "2026-06-07T14:22:20.682645Z"
  },
  {
    "fullCallsign": "KB9VBR",
    "callsign": "KB9VBR",
    "frequency": "7.07486",
    "band": "40m",
    "mode": "ft8",
    "modeDetail": "ft8",
    "time": "14:18",
    "spotter": "VA3XAN",
    "snr": -18,
    "rawText": "DX de VA3XAN: 7074.9 KB9VBR FT8 -18 dB 1418Z (SmartSDR7.0.93)",
    "title": "PSK Reporter spot KB9VBR (7.07486 FT8)",
    "source": "pskreporter",
    "state": "US_WI",
    "spotterState": "CA_ON",
    "qsl": "eqsl",
    "dxcc": 291,
    "entity": "United States of America",
    "cq": "4",
    "continent": "NA",
    "homeDxcc": 291,
    "homeEntity": "United States of America",
    "spotterDxcc": 1,
    "spotterEntity": "Canada",
    "spotterCq": "4",
    "spotterContinent": "NA",
    "triggerComment": "YouTube",
    "received_at": "2026-06-07T14:18:50.583116Z"
  },
  {
    "fullCallsign": "KB9VBR",
    "callsign": "KB9VBR",
    "frequency": "7.074849",
    "band": "40m",
    "mode": "ft8",
    "modeDetail": "ft8",
    "time": "14:06",
    "spotter": "N3AGE-4",
    "rawText": "DX de N3AGE-4: 7074.8 KB9VBR FT8 1406Z (N1DQ-KA9Q-Radio/1.3)",
    "title": "PSK Reporter spot KB9VBR (7.074849 FT8)",
    "source": "pskreporter",
    "state": "US_WI",
    "qsl": "eqsl",
    "dxcc": 291,
    "entity": "United States of America",
    "cq": "4",
    "continent": "NA",
    "homeDxcc": 291,
    "homeEntity": "United States of America",
    "spotterDxcc": 291,
    "spotterEntity": "United States of America",
    "spotterCq": "5",
    "spotterContinent": "NA",
    "triggerComment": "YouTube",
    "received_at": "2026-06-07T14:08:39.060913Z"
  },
  {
    "fullCallsign": "KB9VBR",
    "callsign": "KB9VBR",
    "frequency": "7.081419",
    "band": "40m",
    "mode": "ft8",
    "modeDetail": "ft8",
    "time": "13:58",
    "spotter": "WB5BHS",
    "snr": -21,
    "rawText": "DX de WB5BHS: 7081.4 KB9VBR FT8 -21 dB 1358Z (WSJT-X v2.7.1-devel ial+)",
    "title": "PSK Reporter spot KB9VBR (7.081419 FT8)",
    "source": "pskreporter",
    "state": "US_WI",
    "spotterState": "US_AR",
    "qsl": "eqsl",
    "dxcc": 291,
    "entity": "United States of America",
    "cq": "4",
    "continent": "NA",
    "homeDxcc": 291,
    "homeEntity": "United States of America",
    "spotterDxcc": 291,
    "spotterEntity": "United States of America",
    "spotterCq": "4",
    "spotterContinent": "NA",
    "triggerComment": "YouTube",
    "received_at": "2026-06-07T13:58:54.663000Z"
  },
  {
    "fullCallsign": "KB9VBR",
    "callsign": "KB9VBR",
    "frequency": "7.074852",
    "band": "40m",
    "mode": "ft8",
    "modeDetail": "ft8",
    "time": "13:58",
    "spotter": "WA5PJA",
    "snr": -14,
    "rawText": "DX de WA5PJA: 7074.9 KB9VBR FT8 -14 dB 1358Z (WSJT-X v3.0.0 i+)",
    "title": "PSK Reporter spot KB9VBR (7.074852 FT8)",
    "source": "pskreporter",
    "state": "US_WI",
    "spotterState": "US_TX",
    "qsl": "eqsl",
    "dxcc": 291,
    "entity": "United States of America",
    "cq": "4",
    "continent": "NA",
    "homeDxcc": 291,
    "homeEntity": "United States of America",
    "spotterDxcc": 291,
    "spotterEntity": "United States of America",
    "spotterCq": "4",
    "spotterContinent": "NA",
    "triggerComment": "YouTube",
    "received_at": "2026-06-07T13:58:37.563303Z"
  },
  {
    "fullCallsign": "W8KNX",
    "callsign": "W8KNX",
    "frequency": "7.048336",
    "band": "40m",
    "mode": "ft4",
    "modeDetail": "ft4",
    "time": "11:56",
    "spotter": "WZ7I",
    "snr": 6,
    "rawText": "DX de WZ7I: 7048.3 W8KNX FT4 6 dB 1156Z (CWSL_DIGI 0.88)",
    "title": "PSK Reporter spot W8KNX (7.048336 FT4)",
    "source": "pskreporter",
    "state": "US_MI",
    "spotterState": "US_PA",
    "qsl": "eqsl,lotw",
    "dxcc": 291,
    "entity": "United States of America",
    "cq": "4",
    "continent": "NA",
    "homeDxcc": 291,
    "homeEntity": "United States of America",
    "spotterDxcc": 291,
    "spotterEntity": "United States of America",
    "spotterCq": "5",
    "spotterContinent": "NA",
    "triggerComment": "Everyday Ham",
    "received_at": "2026-06-07T11:57:06.799833Z"
  },
  {
    "fullCallsign": "KI6NAZ",
    "callsign": "KI6NAZ",
    "frequency": "14.105",
    "band": "20m",
    "mode": "varac",
    "modeDetail": "varac",
    "time": "03:21",
    "spotter": "W2JKT",
    "snr": -19,
    "rawText": "DX de W2JKT: 14105.0 KI6NAZ VARAC -19 dB 0321Z (VarAC V13.2.7/Rptr V1.9)",
    "title": "PSK Reporter spot KI6NAZ (14.105 VARAC)",
    "source": "pskreporter",
    "state": "US_CA",
    "spotterState": "US_NC",
    "qsl": "eqsl",
    "dxcc": 291,
    "entity": "United States of America",
    "cq": "3",
    "continent": "NA",
    "homeDxcc": 291,
    "homeEntity": "United States of America",
    "spotterDxcc": 291,
    "spotterEntity": "United States of America",
    "spotterCq": "5",
    "spotterContinent": "NA",
    "triggerComment": "YouTube",
    "received_at": "2026-06-07T03:30:22.769472Z"
  },
  {
    "fullCallsign": "KI6NAZ",
    "callsign": "KI6NAZ",
    "frequency": "14.105",
    "band": "20m",
    "mode": "varac",
    "modeDetail": "varac",
    "time": "03:06",
    "spotter": "KD9PXG",
    "snr": -15,
    "rawText": "DX de KD9PXG: 14105.0 KI6NAZ VARAC -15 dB 0306Z (VarAC V13.2.7/Rptr V1.9)",
    "title": "PSK Reporter spot KI6NAZ (14.105 VARAC)",
    "source": "pskreporter",
    "state": "US_CA",
    "spotterState": "US_WI",
    "qsl": "eqsl",
    "dxcc": 291,
    "entity": "United States of America",
    "cq": "3",
    "continent": "NA",
    "homeDxcc": 291,
    "homeEntity": "United States of America",
    "spotterDxcc": 291,
    "spotterEntity": "United States of America",
    "spotterCq": "4",
    "spotterContinent": "NA",
    "triggerComment": "YouTube",
    "received_at": "2026-06-07T03:20:02.808828Z"
  },
  {
    "fullCallsign": "KI6NAZ",
    "callsign": "KI6NAZ",
    "frequency": "14.105",
    "band": "20m",
    "mode": "varac",
    "modeDetail": "varac",
    "time": "03:06",
    "spotter": "KR4LCU",
    "snr": -6,
    "rawText": "DX de KR4LCU: 14105.0 KI6NAZ VARAC -6 dB 0306Z (VarAC V13.2.7/Rptr V1.9)",
    "title": "PSK Reporter spot KI6NAZ (14.105 VARAC)",
    "source": "pskreporter",
    "state": "US_CA",
    "spotterState": "US_FL",
    "qsl": "eqsl",
    "dxcc": 291,
    "entity": "United States of America",
    "cq": "3",
    "continent": "NA",
    "homeDxcc": 291,
    "homeEntity": "United States of America",
    "spotterDxcc": 291,
    "spotterEntity": "United States of America",
    "spotterCq": "5",
    "spotterContinent": "NA",
    "triggerComment": "YouTube",
    "received_at": "2026-06-07T03:06:27.954377Z"
  },
  {
    "fullCallsign": "W8KNX",
    "callsign": "W8KNX",
    "frequency": "7.0475",
    "band": "40m",
    "mode": "ft4",
    "modeDetail": "ft4",
    "time": "03:06",
    "spotter": "NG7M",
    "snr": -6,
    "rawText": "DX de NG7M-#:    7047.50  W8KNX          FT4   -6 dB  EN74    CQ      0306Z",
    "title": "RBN spot W8KNX (7.0475 FT4)",
    "source": "rbn",
    "state": "US_MI",
    "spotterState": "US_UT",
    "qsl": "eqsl,lotw",
    "dxcc": 291,
    "entity": "United States of America",
    "cq": "4",
    "continent": "NA",
    "homeDxcc": 291,
    "homeEntity": "United States of America",
    "spotterDxcc": 291,
    "spotterEntity": "United States of America",
    "spotterCq": "3",
    "spotterContinent": "NA",
    "triggerComment": "Everyday Ham",
    "received_at": "2026-06-07T03:06:06.017021Z"
  },
  {
    "fullCallsign": "W8KNX",
    "callsign": "W8KNX",
    "frequency": "7.07489",
    "band": "40m",
    "mode": "ft8",
    "modeDetail": "ft8",
    "time": "02:48",
    "spotter": "N0DCA",
    "snr": -5,
    "rawText": "DX de N0DCA: 7074.9 W8KNX FT8 -5 dB 0248Z (WSJT-X v2.7.1-devel i+)",
    "title": "PSK Reporter spot W8KNX (7.07489 FT8)",
    "source": "pskreporter",
    "state": "US_MI",
    "spotterState": "US_NE",
    "qsl": "eqsl,lotw",
    "dxcc": 291,
    "entity": "United States of America",
    "cq": "4",
    "continent": "NA",
    "homeDxcc": 291,
    "homeEntity": "United States of America",
    "spotterDxcc": 291,
    "spotterEntity": "United States of America",
    "spotterCq": "4",
    "spotterContinent": "NA",
    "triggerComment": "Everyday Ham",
    "received_at": "2026-06-07T02:48:35.793923Z"
  },
  {
    "fullCallsign": "KI6NAZ",
    "callsign": "KI6NAZ",
    "frequency": "14.105",
    "band": "20m",
    "mode": "varac",
    "modeDetail": "varac",
    "time": "02:35",
    "spotter": "WB7OND",
    "snr": -2,
    "rawText": "DX de WB7OND: 14105.0 KI6NAZ VARAC -2 dB 0235Z (VarAC V13.2.7/Rptr V1.9)",
    "title": "PSK Reporter spot KI6NAZ (14.105 VARAC)",
    "source": "pskreporter",
    "state": "US_CA",
    "spotterState": "US_NC",
    "qsl": "eqsl",
    "dxcc": 291,
    "entity": "United States of America",
    "cq": "3",
    "continent": "NA",
    "homeDxcc": 291,
    "homeEntity": "United States of America",
    "spotterDxcc": 291,
    "spotterEntity": "United States of America",
    "spotterCq": "5",
    "spotterContinent": "NA",
    "triggerComment": "YouTube",
    "received_at": "2026-06-07T02:38:15.173400Z"
  },
  {
    "fullCallsign": "KI6NAZ",
    "callsign": "KI6NAZ",
    "frequency": "14.105",
    "band": "20m",
    "mode": "varac",
    "modeDetail": "varac",
    "time": "02:05",
    "spotter": "KH7BR",
    "snr": -20,
    "rawText": "DX de KH7BR: 14105.0 KI6NAZ VARAC -20 dB 0205Z (VarAC V13.2.7/Rptr V1.9)",
    "title": "PSK Reporter spot KI6NAZ (14.105 VARAC)",
    "source": "pskreporter",
    "state": "US_CA",
    "spotterState": "US_HI",
    "qsl": "eqsl",
    "dxcc": 291,
    "entity": "United States of America",
    "cq": "3",
    "continent": "NA",
    "homeDxcc": 291,
    "homeEntity": "United States of America",
    "spotterDxcc": 110,
    "spotterEntity": "Hawaii",
    "spotterCq": "31",
    "spotterContinent": "OC",
    "triggerComment": "YouTube",
    "received_at": "2026-06-07T02:05:32.544343Z"
  },
  {
    "fullCallsign": "KB9VBR",
    "callsign": "KB9VBR",
    "frequency": "7.074",
    "band": "40m",
    "mode": "ft8",
    "modeDetail": "ft8",
    "time": "01:59",
    "spotter": "K9IMM",
    "snr": -3,
    "rawText": "DX de K9IMM-#:   7074.00  KB9VBR         FT8   -3 dB  EN64    CQ      0159Z",
    "title": "RBN spot KB9VBR (7.074 FT8)",
    "source": "rbn",
    "state": "US_WI",
    "spotterState": "US_WI",
    "qsl": "eqsl",
    "dxcc": 291,
    "entity": "United States of America",
    "cq": "4",
    "continent": "NA",
    "homeDxcc": 291,
    "homeEntity": "United States of America",
    "spotterDxcc": 291,
    "spotterEntity": "United States of America",
    "spotterCq": "4",
    "spotterContinent": "NA",
    "triggerComment": "YouTube",
    "received_at": "2026-06-07T01:59:42.822310Z"
  },
  {
    "fullCallsign": "KI6NAZ",
    "callsign": "KI6NAZ",
    "frequency": "14.105",
    "band": "20m",
    "mode": "varac",
    "modeDetail": "varac",
    "time": "01:48",
    "spotter": "ZL2TNB",
    "snr": -19,
    "rawText": "DX de ZL2TNB: 14105.0 KI6NAZ VARAC -19 dB 0148Z (VarAC V13.2.7/Rptr V1.9)",
    "title": "PSK Reporter spot KI6NAZ (14.105 VARAC)",
    "source": "pskreporter",
    "state": "US_CA",
    "qsl": "eqsl",
    "dxcc": 291,
    "entity": "United States of America",
    "cq": "3",
    "continent": "NA",
    "homeDxcc": 291,
    "homeEntity": "United States of America",
    "spotterDxcc": 170,
    "spotterEntity": "New Zealand",
    "spotterCq": "32",
    "spotterContinent": "OC",
    "triggerComment": "YouTube",
    "received_at": "2026-06-07T01:53:06.755850Z"
  },
  {
    "fullCallsign": "KB9VBR",
    "callsign": "KB9VBR",
    "frequency": "10.13762",
    "band": "30m",
    "mode": "ft8",
    "modeDetail": "ft8",
    "time": "01:43",
    "spotter": "K4QVH",
    "snr": -4,
    "rawText": "DX de K4QVH: 10137.6 KB9VBR FT8 -4 dB 0143Z (JTDX v2.2.159 i)",
    "title": "PSK Reporter spot KB9VBR (10.13762 FT8)",
    "source": "pskreporter",
    "state": "US_WI",
    "spotterState": "US_GA",
    "qsl": "eqsl",
    "dxcc": 291,
    "entity": "United States of America",
    "cq": "4",
    "continent": "NA",
    "homeDxcc": 291,
    "homeEntity": "United States of America",
    "spotterDxcc": 291,
    "spotterEntity": "United States of America",
    "spotterCq": "5",
    "spotterContinent": "NA",
    "triggerComment": "YouTube",
    "received_at": "2026-06-07T01:46:57.684065Z"
  },
  {
    "fullCallsign": "KB9VBR",
    "callsign": "KB9VBR",
    "frequency": "10.136",
    "band": "30m",
    "mode": "ft8",
    "modeDetail": "ft8",
    "time": "01:36",
    "spotter": "KM3T-3",
    "snr": 12,
    "rawText": "DX de KM3T-3-#: 10136.00  KB9VBR         FT8   12 dB          CQ      0136Z",
    "title": "RBN spot KB9VBR (10.136 FT8)",
    "source": "rbn",
    "state": "US_WI",
    "qsl": "eqsl",
    "dxcc": 291,
    "entity": "United States of America",
    "cq": "4",
    "continent": "NA",
    "homeDxcc": 291,
    "homeEntity": "United States of America",
    "spotterDxcc": 291,
    "spotterEntity": "United States of America",
    "spotterCq": "5",
    "spotterContinent": "NA",
    "triggerComment": "YouTube",
    "received_at": "2026-06-07T01:36:14.481104Z"
  },
  {
    "fullCallsign": "KI6NAZ",
    "callsign": "KI6NAZ",
    "frequency": "14.105",
    "band": "20m",
    "mode": "varac",
    "modeDetail": "varac",
    "time": "01:32",
    "spotter": "WB7OND",
    "snr": -1,
    "rawText": "DX de WB7OND: 14105.0 KI6NAZ VARAC -1 dB 0132Z (VarAC V13.2.7/Rptr V1.9)",
    "title": "PSK Reporter spot KI6NAZ (14.105 VARAC)",
    "source": "pskreporter",
    "state": "US_CA",
    "spotterState": "US_NC",
    "qsl": "eqsl",
    "dxcc": 291,
    "entity": "United States of America",
    "cq": "3",
    "continent": "NA",
    "homeDxcc": 291,
    "homeEntity": "United States of America",
    "spotterDxcc": 291,
    "spotterEntity": "United States of America",
    "spotterCq": "5",
    "spotterContinent": "NA",
    "triggerComment": "YouTube",
    "received_at": "2026-06-07T01:35:16.900536Z"
  },
  {
    "fullCallsign": "KB9VBR",
    "callsign": "KB9VBR",
    "frequency": "10.137509",
    "band": "30m",
    "mode": "ft8",
    "modeDetail": "ft8",
    "time": "01:22",
    "spotter": "KC2G",
    "rawText": "DX de KC2G: 10137.5 KB9VBR FT8 0122Z (N1DQ-KA9Q-Radio/1.3)",
    "title": "PSK Reporter spot KB9VBR (10.137509 FT8)",
    "source": "pskreporter",
    "state": "US_WI",
    "spotterState": "US_NJ",
    "qsl": "eqsl",
    "dxcc": 291,
    "entity": "United States of America",
    "cq": "4",
    "continent": "NA",
    "homeDxcc": 291,
    "homeEntity": "United States of America",
    "spotterDxcc": 291,
    "spotterEntity": "United States of America",
    "spotterCq": "5",
    "spotterContinent": "NA",
    "triggerComment": "YouTube",
    "received_at": "2026-06-07T01:26:00.074103Z"
  },
  {
    "fullCallsign": "KB9VBR",
    "callsign": "KB9VBR",
    "frequency": "10.136",
    "band": "30m",
    "mode": "ft8",
    "modeDetail": "ft8",
    "time": "01:15",
    "spotter": "OE9GHV",
    "rawText": "01:15 KB9VBR in US-4354 (Point Beach State Forest) 10.1360 FT8: RBN -18 dB via OE9GHV-#",
    "title": "POTA KB9VBR in US-4354 (10.1360 FT8)",
    "comment": "RBN -18 dB via OE9GHV-#",
    "source": "pota",
    "state": [
      "US_WI"
    ],
    "wwffRef": "US-4354",
    "wwffDivision": "US",
    "wwffName": "Point Beach State Forest",
    "qsl": "eqsl",
    "dxcc": 291,
    "entity": "United States of America",
    "cq": "4",
    "continent": "NA",
    "homeDxcc": 291,
    "homeEntity": "United States of America",
    "spotterDxcc": 206,
    "spotterEntity": "Austria",
    "spotterCq": "15",
    "spotterContinent": "EU",
    "triggerComment": "YouTube",
    "received_at": "2026-06-07T01:15:48.125079Z"
  },
  {
    "fullCallsign": "KB9VBR",
    "callsign": "KB9VBR",
    "frequency": "10.137662",
    "band": "30m",
    "mode": "ft8",
    "modeDetail": "ft8",
    "time": "01:04",
    "spotter": "W3GO",
    "snr": -14,
    "rawText": "DX de W3GO: 10137.7 KB9VBR FT8 -14 dB 0104Z (WSJT-X v3.0.0 i+)",
    "title": "PSK Reporter spot KB9VBR (10.137662 FT8)",
    "source": "pskreporter",
    "state": "US_WI",
    "spotterState": "US_NJ",
    "qsl": "eqsl",
    "dxcc": 291,
    "entity": "United States of America",
    "cq": "4",
    "continent": "NA",
    "homeDxcc": 291,
    "homeEntity": "United States of America",
    "spotterDxcc": 291,
    "spotterEntity": "United States of America",
    "spotterCq": "5",
    "spotterContinent": "NA",
    "triggerComment": "YouTube",
    "received_at": "2026-06-07T01:05:39.038109Z"
  },
  {
    "fullCallsign": "KB9VBR",
    "callsign": "KB9VBR",
    "frequency": "10.136",
    "band": "30m",
    "mode": "ft8",
    "modeDetail": "ft8",
    "time": "00:55",
    "spotter": "K7CO",
    "snr": -12,
    "rawText": "DX de K7CO-#:   10136.00  KB9VBR         FT8  -12 dB  EN64    CQ      0055Z",
    "title": "RBN spot KB9VBR (10.136 FT8)",
    "source": "rbn",
    "state": "US_WI",
    "spotterState": "US_UT",
    "qsl": "eqsl",
    "dxcc": 291,
    "entity": "United States of America",
    "cq": "4",
    "continent": "NA",
    "homeDxcc": 291,
    "homeEntity": "United States of America",
    "spotterDxcc": 291,
    "spotterEntity": "United States of America",
    "spotterCq": "3",
    "spotterContinent": "NA",
    "triggerComment": "YouTube",
    "received_at": "2026-06-07T00:55:33.235417Z"
  },
  {
    "fullCallsign": "KI6NAZ",
    "callsign": "KI6NAZ",
    "frequency": "14.079507",
    "band": "20m",
    "mode": "js8",
    "modeDetail": "js8",
    "time": "00:42",
    "spotter": "K3FHP",
    "snr": -16,
    "rawText": "DX de K3FHP: 14079.5 KI6NAZ JS8 -16 dB 0042Z (JS8Call v2.4.0)",
    "title": "PSK Reporter spot KI6NAZ (14.079507 JS8)",
    "source": "pskreporter",
    "state": "US_CA",
    "spotterState": "US_FL",
    "qsl": "eqsl",
    "dxcc": 291,
    "entity": "United States of America",
    "cq": "3",
    "continent": "NA",
    "homeDxcc": 291,
    "homeEntity": "United States of America",
    "spotterDxcc": 291,
    "spotterEntity": "United States of America",
    "spotterCq": "5",
    "spotterContinent": "NA",
    "triggerComment": "YouTube",
    "received_at": "2026-06-07T00:44:55.498893Z"
  },
  {
    "fullCallsign": "KI6NAZ",
    "callsign": "KI6NAZ",
    "frequency": "14.078952",
    "band": "20m",
    "mode": "js8",
    "modeDetail": "js8",
    "time": "00:22",
    "spotter": "EA8-DF4UE",
    "snr": -10,
    "rawText": "DX de EA8-DF4UE: 14079.0 KI6NAZ JS8 -10 dB 0022Z (UberSDR 0.1.51)",
    "title": "PSK Reporter spot KI6NAZ (14.078952 JS8)",
    "source": "pskreporter",
    "state": "US_CA",
    "qsl": "eqsl",
    "dxcc": 291,
    "entity": "United States of America",
    "cq": "3",
    "continent": "NA",
    "homeDxcc": 291,
    "homeEntity": "United States of America",
    "triggerComment": "YouTube",
    "received_at": "2026-06-07T00:23:08.957476Z"
  },
  {
    "fullCallsign": "KI6NAZ",
    "callsign": "KI6NAZ",
    "frequency": "14.105",
    "band": "20m",
    "mode": "varac",
    "modeDetail": "varac",
    "time": "00:09",
    "spotter": "FM4TI",
    "snr": -12,
    "rawText": "DX de FM4TI: 14105.0 KI6NAZ VARAC -12 dB 0009Z (VarAC V13.2.7/Rptr V1.9)",
    "title": "PSK Reporter spot KI6NAZ (14.105 VARAC)",
    "source": "pskreporter",
    "state": "US_CA",
    "qsl": "eqsl",
    "dxcc": 291,
    "entity": "United States of America",
    "cq": "3",
    "continent": "NA",
    "homeDxcc": 291,
    "homeEntity": "United States of America",
    "spotterDxcc": 84,
    "spotterEntity": "Martinique",
    "spotterCq": "8",
    "spotterContinent": "NA",
    "triggerComment": "YouTube",
    "received_at": "2026-06-07T00:14:49.958072Z"
  },
  {
    "fullCallsign": "KI6NAZ",
    "callsign": "KI6NAZ",
    "frequency": "14.105",
    "band": "20m",
    "mode": "varac",
    "modeDetail": "varac",
    "time": "23:53",
    "spotter": "WB5KUO",
    "snr": -8,
    "rawText": "DX de WB5KUO: 14105.0 KI6NAZ VARAC -8 dB 2353Z (VarAC V13.2.7/Rptr V1.9)",
    "title": "PSK Reporter spot KI6NAZ (14.105 VARAC)",
    "source": "pskreporter",
    "state": "US_CA",
    "spotterState": "US_TX",
    "qsl": "eqsl",
    "dxcc": 291,
    "entity": "United States of America",
    "cq": "3",
    "continent": "NA",
    "homeDxcc": 291,
    "homeEntity": "United States of America",
    "spotterDxcc": 291,
    "spotterEntity": "United States of America",
    "spotterCq": "4",
    "spotterContinent": "NA",
    "triggerComment": "YouTube",
    "received_at": "2026-06-07T00:04:17.466384Z"
  },
  {
    "fullCallsign": "KI6NAZ",
    "callsign": "KI6NAZ",
    "frequency": "14.105",
    "band": "20m",
    "mode": "varac",
    "modeDetail": "varac",
    "time": "23:53",
    "spotter": "K4XAI",
    "snr": -12,
    "rawText": "DX de K4XAI: 14105.0 KI6NAZ VARAC -12 dB 2353Z (VarAC V13.2.7/Rptr V1.9)",
    "title": "PSK Reporter spot KI6NAZ (14.105 VARAC)",
    "source": "pskreporter",
    "state": "US_CA",
    "spotterState": "US_SC",
    "qsl": "eqsl",
    "dxcc": 291,
    "entity": "United States of America",
    "cq": "3",
    "continent": "NA",
    "homeDxcc": 291,
    "homeEntity": "United States of America",
    "spotterDxcc": 291,
    "spotterEntity": "United States of America",
    "spotterCq": "5",
    "spotterContinent": "NA",
    "triggerComment": "YouTube",
    "received_at": "2026-06-06T23:54:01.501383Z"
  },
  {
    "fullCallsign": "N1RWJ",
    "callsign": "N1RWJ",
    "frequency": "14.054",
    "band": "20m",
    "mode": "cw",
    "modeDetail": "cw",
    "time": "23:45",
    "spotter": "K9IMM",
    "snr": 28,
    "speed": 25,
    "rawText": "DX de K9IMM-#:  14054.00  N1RWJ          CW    28 dB  25 WPM  CQ      2345Z",
    "title": "RBN spot N1RWJ (14.054 CW)",
    "source": "rbn",
    "state": "US_RI",
    "spotterState": "US_WI",
    "qsl": "eqsl,lotw",
    "dxcc": 291,
    "entity": "United States of America",
    "cq": "5",
    "continent": "NA",
    "homeDxcc": 291,
    "homeEntity": "United States of America",
    "spotterDxcc": 291,
    "spotterEntity": "United States of America",
    "spotterCq": "4",
    "spotterContinent": "NA",
    "triggerComment": "EDH Discord",
    "received_at": "2026-06-06T23:45:54.979357Z"
  },
  {
    "fullCallsign": "KI6NAZ",
    "callsign": "KI6NAZ",
    "frequency": "14.105",
    "band": "20m",
    "mode": "varac",
    "modeDetail": "varac",
    "time": "23:24",
    "spotter": "KC0TAF",
    "snr": -15,
    "rawText": "DX de KC0TAF: 14105.0 KI6NAZ VARAC -15 dB 2324Z (VarAC V13.2.7/Rptr V1.9)",
    "title": "PSK Reporter spot KI6NAZ (14.105 VARAC)",
    "source": "pskreporter",
    "state": "US_CA",
    "spotterState": "US_MN",
    "qsl": "eqsl",
    "dxcc": 291,
    "entity": "United States of America",
    "cq": "3",
    "continent": "NA",
    "homeDxcc": 291,
    "homeEntity": "United States of America",
    "spotterDxcc": 291,
    "spotterEntity": "United States of America",
    "spotterCq": "4",
    "spotterContinent": "NA",
    "triggerComment": "YouTube",
    "received_at": "2026-06-06T23:37:56.108431Z"
  },
  {
    "fullCallsign": "KI6NAZ",
    "callsign": "KI6NAZ",
    "frequency": "14.105",
    "band": "20m",
    "mode": "varac",
    "modeDetail": "varac",
    "time": "23:14",
    "spotter": "KI6NAZ",
    "rawText": "DX de KI6NAZ: 14105.0 KI6NAZ VARAC 2314Z (VarAC V13.2.7/Rptr V1.9)",
    "title": "PSK Reporter spot KI6NAZ (14.105 VARAC)",
    "source": "pskreporter",
    "state": "US_CA",
    "spotterState": "US_CA",
    "qsl": "eqsl",
    "dxcc": 291,
    "entity": "United States of America",
    "cq": "3",
    "continent": "NA",
    "homeDxcc": 291,
    "homeEntity": "United States of America",
    "spotterDxcc": 291,
    "spotterEntity": "United States of America",
    "spotterCq": "3",
    "spotterContinent": "NA",
    "triggerComment": "YouTube",
    "received_at": "2026-06-06T23:26:36.844654Z"
  }
]